Workbook
Name Slicer_Status: #N/A

Sheet README
A1: Excel Practice — Sales Analysis (30 questions)
A3: Dataset: 250 orders, Jan–Dec 2025, 4 regions, 12 cities, 8 salespeople, 12 products. All data is made up for practice.
A5: How to use
A6: 1. Open the 'Questions' sheet — each question tells you which function to use and where to apply it.
A7: 2. Work on 'Sales_Data'. Yellow headers (columns N–S) are empty columns for YOU to fill with formulas.
A8: 3. Other practice sheets: Product_Master (lookups), Targets (lookups), Messy_Data (cleaning).
A9: 4. Stuck or finished? Check 'Answer_Key' (live answers + formulas) and 'Answer_Tables' (full expected tables).
A11: Notes
A12: • Revenue = Quantity × Unit Price × (1 − Discount), across ALL orders (including returned/cancelled) unless a question says Delivered only.
A13: • Blue font = hardcoded input. Black = formula.
A14: • Tip: do each question first with a helper column, then try the same thing with SUMPRODUCT to see two ways.

Sheet Questions
A1: Q# | B1: Level | C1: Skill | D1: Question | E1: Functions / tools to use | F1: Where to apply it
A2: 1 | B2: Beginner | C2: Basic arithmetic | D2: Add a Revenue column: Quantity × Unit Price × (1 − Discount) for every order. | E2: Operators (* , -), relative vs absolute references, fill-down | F2: Sales_Data → column N (yellow header)
A3: 2 | B3: Beginner | C3: Counting & summing | D3: (a) Total number of orders (b) Total units sold. | E3: COUNTA, SUM | F3: Any blank cell, or a summary sheet
A4: 3 | B4: Beginner | C4: Statistics | D4: (a) Average revenue per order (b) Highest single-order revenue (c) Lowest single-order revenue. | E4: AVERAGE, MAX, MIN | F4: Revenue column N
A5: 4 | B5: Beginner | C5: Conditional count | D5: How many orders are Delivered, Returned and Cancelled? | E5: COUNTIF | F5: Status column M
A6: 5 | B6: Beginner | C6: Conditional sum | D6: (a) Total revenue of the West region. (b) Net revenue — Delivered orders only. | E6: SUMIF, SUMIFS | F6: Region D / Status M with Revenue N
A7: 6 | B7: Beginner | C7: Date functions | D7: Add a Month column (Jan, Feb…). How many orders were placed in March? | E7: MONTH, TEXT(date,"mmm"), COUNTIF | F7: Sales_Data → column O
A8: 7 | B8: Beginner | C8: IF logic | D8: Order Size: 'High Value' if revenue > 15,000, 'Medium' if ≥ 5,000, else 'Low'. How many High Value orders? | E8: IF (nested), COUNTIF | F8: Sales_Data → column P
A9: 8 | B9: Intermediate | C9: Multi-criteria sum | D9: Revenue from Electronics, in the North region, Delivered orders only. | E9: SUMIFS | F9: Any blank cell
A10: 9 | B10: Intermediate | C10: Conditional average | D10: Average discount given on UPI payments, and on COD payments. | E10: AVERAGEIF / AVERAGEIFS | F10: Payment Mode L, Discount K
A11: 10 | B11: Intermediate | C11: Lookup the max | D11: Which Order ID has the highest revenue? | E11: INDEX + MATCH + MAX | F11: Order ID A, Revenue N
A12: 11 | B12: Intermediate | C12: Lookups across sheets | D12: Bring Cost Price from Product_Master into the data (do it once with VLOOKUP, once with INDEX+MATCH — results must match). Then Profit = Revenue − Quantity × Cost. Total profit? | E12: VLOOKUP (exact match), INDEX+MATCH | F12: Sales_Data → columns Q (Cost Price) and R (Profit)
... A31: 30 | B31: Data cleaning | C31: Duplicates | D31: After cleaning, how many unique customers are there? | E31: COUNTIF to flag duplicates, Data → Remove Duplicates, SUMPRODUCT(1/COUNTIF) | F31: Cleaned name column

Sheet Sales_Data
A1: Order ID | B1: Order Date | C1: Delivery Date | D1: Region | E1: City | F1: Salesperson | G1: Category | H1: Product | I1: Quantity | J1: Unit Price (₹) | K1: Discount % | L1: Payment Mode | M1: Status | N1: Revenue (₹) ← add | O1: Month ← add | P1: Order Size ← add | Q1: Cost Price ← add | R1: Profit ← add | S1: Delivery Days ← add | T1: day of week
A2: ORD1001 | B2: 45659 | C2: 45664 | D2: East | E2: Bhubaneswar | F2: Rohit Das | G2: Stationery | H2: Gel Pen Box | I2: 8 | J2: 249 | K2: 0.1 | L2: COD | M2: Delivered | N2: =Table1[[#This Row],[Quantity]]*Table1[[#This Row],[Unit Price (₹)]]*(1-Table1[[#This Row],[Discount %]]) -> 1792.8 | O2: =TEXT(Table1[[#This Row],[Order Date]],"mmmm") -> January | P2: =IF(Table1[[#This Row],[Revenue (₹) ← add]]>=15000,"High Value",IF(Table1[[#This Row],[Revenue (₹) ← add]]>=5000,"Medium","Low")) -> Low | Q2: =VLOOKUP(Table1[[#This Row],[Product]],Table2[],4,FALSE) -> 120 | R2: =Table1[[#This Row],[Revenue (₹) ← add]]-Table1[[#This Row],[Cost Price ← add]] -> 1672.8 | S2: =IF(C2="", "",Table1[[#This Row],[Delivery Date]]-Table1[[#This Row],[Order Date]]) -> 5 | T2: =TEXT(Table1[[#This Row],[Order Date]],"DDDD") -> Thursday
A3: ORD1002 | B3: 45664 | C3: 45671 | D3: East | E3: Kolkata | F3: Rohit Das | G3: Clothing | H3: Denim Jacket | I3: 4 | J3: 2999 | K3: 0 | L3: COD | M3: Delivered | N3: =Table1[[#This Row],[Quantity]]*Table1[[#This Row],[Unit Price (₹)]]*(1-Table1[[#This Row],[Discount %]]) -> 11996 | O3: =TEXT(Table1[[#This Row],[Order Date]],"mmmm") -> January | P3: =IF(Table1[[#This Row],[Revenue (₹) ← add]]>=15000,"High Value",IF(Table1[[#This Row],[Revenue (₹) ← add]]>=5000,"Medium","Low")) -> Medium | Q3: =VLOOKUP(Table1[[#This Row],[Product]],Table2[],4,FALSE) -> 1700 | R3: =Table1[[#This Row],[Revenue (₹) ← add]]-Table1[[#This Row],[Cost Price ← add]] -> 10296 | S3: =IF(C3="", "",Table1[[#This Row],[Delivery Date]]-Table1[[#This Row],[Order Date]]) -> 7 | T3: =TEXT(Table1[[#This Row],[Order Date]],"DDDD") -> Tuesday
A4: ORD1003 | B4: 45665 | C4: 45668 | D4: East | E4: Kolkata | F4: Rohit Das | G4: Furniture | H4: Study Desk | I4: 2 | J4: 8499 | K4: 0.05 | L4: UPI | M4: Delivered | N4: =Table1[[#This Row],[Quantity]]*Table1[[#This Row],[Unit Price (₹)]]*(1-Table1[[#This Row],[Discount %]]) -> 16148.1 | O4: =TEXT(Table1[[#This Row],[Order Date]],"mmmm") -> January | P4: =IF(Table1[[#This Row],[Revenue (₹) ← add]]>=15000,"High Value",IF(Table1[[#This Row],[Revenue (₹) ← add]]>=5000,"Medium","Low")) -> High Value | Q4: =VLOOKUP(Table1[[#This Row],[Product]],Table2[],4,FALSE) -> 5200 | R4: =Table1[[#This Row],[Revenue (₹) ← add]]-Table1[[#This Row],[Cost Price ← add]] -> 10948.1 | S4: =IF(C4="", "",Table1[[#This Row],[Delivery Date]]-Table1[[#This Row],[Order Date]]) -> 3 | T4: =TEXT(Table1[[#This Row],[Order Date]],"DDDD") -> Wednesday | V4: Total orders | W4: =COUNTA(Table1[Order ID]) -> 250
A5: ORD1004 | B5: 45668 | C5: 45677 | D5: South | E5: Hyderabad | F5: Karthik Iyer | G5: Clothing | H5: Cotton T-Shirt | I5: 5 | J5: 599 | K5: 0 | L5: COD | M5: Delivered | N5: =Table1[[#This Row],[Quantity]]*Table1[[#This Row],[Unit Price (₹)]]*(1-Table1[[#This Row],[Discount %]]) -> 2995 | O5: =TEXT(Table1[[#This Row],[Order Date]],"mmmm") -> January | P5: =IF(Table1[[#This Row],[Revenue (₹) ← add]]>=15000,"High Value",IF(Table1[[#This Row],[Revenue (₹) ← add]]>=5000,"Medium","Low")) -> Low | Q5: =VLOOKUP(Table1[[#This Row],[Product]],Table2[],4,FALSE) -> 300 | R5: =Table1[[#This Row],[Revenue (₹) ← add]]-Table1[[#This Row],[Cost Price ← add]] -> 2695 | S5: =IF(C5="", "",Table1[[#This Row],[Delivery Date]]-Table1[[#This Row],[Order Date]]) -> 9 | T5: =TEXT(Table1[[#This Row],[Order Date]],"DDDD") -> Saturday | V5: Total Unit Sold | W5: =SUM(Table1[Quantity]) -> 1357
A6: ORD1005 | B6: 45668 | C6: 45673 | D6: South | E6: Chennai | F6: Meera Nair | G6: Stationery | H6: Gel Pen Box | I6: 8 | J6: 249 | K6: 0.1 | L6: COD | M6: Delivered | N6: =Table1[[#This Row],[Quantity]]*Table1[[#This Row],[Unit Price (₹)]]*(1-Table1[[#This Row],[Discount %]]) -> 1792.8 | O6: =TEXT(Table1[[#This Row],[Order Date]],"mmmm") -> January | P6: =IF(Table1[[#This Row],[Revenue (₹) ← add]]>=15000,"High Value",IF(Table1[[#This Row],[Revenue (₹) ← add]]>=5000,"Medium","Low")) -> Low | Q6: =INDEX(Table2[Cost Price (₹)],MATCH(H5,Table2[Product],0)) -> 300 | R6: =Table1[[#This Row],[Revenue (₹) ← add]]-Table1[[#This Row],[Cost Price ← add]] -> 1492.8 | S6: =IF(C6="", "",Table1[[#This Row],[Delivery Date]]-Table1[[#This Row],[Order Date]]) -> 5 | T6: =TEXT(Table1[[#This Row],[Order Date]],"DDDD") -> Saturday | V6: Average Revenue per order | W6: =AVERAGE(Table1[Revenue (₹) ← add]) -> 6993.1882
A7: ORD1006 | B7: 45669 | D7: East | E7: Bhubaneswar | F7: Ananya Sen | G7: Clothing | H7: Denim Jacket | I7: 2 | J7: 2999 | K7: 0.2 | L7: Net Banking | M7: Cancelled | N7: =Table1[[#This Row],[Quantity]]*Table1[[#This Row],[Unit Price (₹)]]*(1-Table1[[#This Row],[Discount %]]) -> 4798.4 | O7: =TEXT(Table1[[#This Row],[Order Date]],"mmmm") -> January | P7: =IF(Table1[[#This Row],[Revenue (₹) ← add]]>=15000,"High Value",IF(Table1[[#This Row],[Revenue (₹) ← add]]>=5000,"Medium","Low")) -> Low | Q7: =VLOOKUP(Table1[[#This Row],[Product]],Table2[],4,FALSE) -> 1700 | R7: =Table1[[#This Row],[Revenue (₹) ← add]]-Table1[[#This Row],[Cost Price ← add]] -> 3098.4 | S7: =IF(C7="", "",Table1[[#This Row],[Delivery Date]]-Table1[[#This Row],[Order Date]]) | T7: =TEXT(Table1[[#This Row],[Order Date]],"DDDD") -> Sunday | V7: Highest single-order revenue | W7: =MAX(Table1[Revenue (₹) ← add]) -> 25497
A8: ORD1007 | B8: 45669 | C8: 45675 | D8: East | E8: Kolkata | F8: Ananya Sen | G8: Electronics | H8: Power Bank | I8: 3 | J8: 1499 | K8: 0.1 | L8: UPI | M8: Returned | N8: =Table1[[#This Row],[Quantity]]*Table1[[#This Row],[Unit Price (₹)]]*(1-Table1[[#This Row],[Discount %]]) -> 4047.3 | O8: =TEXT(Table1[[#This Row],[Order Date]],"mmmm") -> January | P8: =IF(Table1[[#This Row],[Revenue (₹) ← add]]>=15000,"High Value",IF(Table1[[#This Row],[Revenue (₹) ← add]]>=5000,"Medium","Low")) -> Low | Q8: =VLOOKUP(Table1[[#This Row],[Product]],Table2[],4,FALSE) -> 850 | R8: =Table1[[#This Row],[Revenue (₹) ← add]]-Table1[[#This Row],[Cost Price ← add]] -> 3197.3 | S8: =IF(C8="", "",Table1[[#This Row],[Delivery Date]]-Table1[[#This Row],[Order Date]]) -> 6 | T8: =TEXT(Table1[[#This Row],[Order Date]],"DDDD") -> Sunday | V8: Lowest single-order revenue | W8: =MIN(Table1[Revenue (₹) ← add]) -> 719.1
A9: ORD1008 | B9: 45669 | C9: 45677 | D9: East | E9: Bhubaneswar | F9: Ananya Sen | G9: Furniture | H9: Study Desk | I9: 2 | J9: 8499 | K9: 0 | L9: UPI | M9: Delivered | N9: =Table1[[#This Row],[Quantity]]*Table1[[#This Row],[Unit Price (₹)]]*(1-Table1[[#This Row],[Discount %]]) -> 16998 | O9: =TEXT(Table1[[#This Row],[Order Date]],"mmmm") -> January | P9: =IF(Table1[[#This Row],[Revenue (₹) ← add]]>=15000,"High Value",IF(Table1[[#This Row],[Revenue (₹) ← add]]>=5000,"Medium","Low")) -> High Value | Q9: =VLOOKUP(Table1[[#This Row],[Product]],Table2[],4,FALSE) -> 5200 | R9: =Table1[[#This Row],[Revenue (₹) ← add]]-Table1[[#This Row],[Cost Price ← add]] -> 11798 | S9: =IF(C9="", "",Table1[[#This Row],[Delivery Date]]-Table1[[#This Row],[Order Date]]) -> 8 | T9: =TEXT(Table1[[#This Row],[Order Date]],"DDDD") -> Sunday | V9: Deliverd | W9: =COUNTIF(M2:M251,"Delivered") -> 217
A10: ORD1009 | B10: 45671 | C10: 45678 | D10: North | E10: Delhi | F10: Simran Kaur | G10: Furniture | H10: Study Desk | I10: 2 | J10: 8499 | K10: 0 | L10: Debit Card | M10: Delivered | N10: =Table1[[#This Row],[Quantity]]*Table1[[#This Row],[Unit Price (₹)]]*(1-Table1[[#This Row],[Discount %]]) -> 16998 | O10: =TEXT(Table1[[#This Row],[Order Date]],"mmmm") -> January | P10: =IF(Table1[[#This Row],[Revenue (₹) ← add]]>=15000,"High Value",IF(Table1[[#This Row],[Revenue (₹) ← add]]>=5000,"Medium","Low")) -> High Value | Q10: =VLOOKUP(Table1[[#This Row],[Product]],Table2[],4,FALSE) -> 5200 | R10: =Table1[[#This Row],[Revenue (₹) ← add]]-Table1[[#This Row],[Cost Price ← add]] -> 11798 | S10: =IF(C10="", "",Table1[[#This Row],[Delivery Date]]-Table1[[#This Row],[Order Date]]) -> 7 | T10: =TEXT(Table1[[#This Row],[Order Date]],"DDDD") -> Tuesday | V10: Returned | W10: =COUNTIF(M2:M251,"Returned") -> 15
A11: ORD1010 | B11: 45672 | D11: South | E11: Bengaluru | F11: Karthik Iyer | G11: Electronics | H11: Wireless Mouse | I11: 3 | J11: 799 | K11: 0.1 | L11: Credit Card | M11: Cancelled | N11: =Table1[[#This Row],[Quantity]]*Table1[[#This Row],[Unit Price (₹)]]*(1-Table1[[#This Row],[Discount %]]) -> 2157.3 | O11: =TEXT(Table1[[#This Row],[Order Date]],"mmmm") -> January | P11: =IF(Table1[[#This Row],[Revenue (₹) ← add]]>=15000,"High Value",IF(Table1[[#This Row],[Revenue (₹) ← add]]>=5000,"Medium","Low")) -> Low | Q11: =VLOOKUP(Table1[[#This Row],[Product]],Table2[],4,FALSE) -> 450 | R11: =Table1[[#This Row],[Revenue (₹) ← add]]-Table1[[#This Row],[Cost Price ← add]] -> 1707.3 | S11: =IF(C11="", "",Table1[[#This Row],[Delivery Date]]-Table1[[#This Row],[Order Date]]) | T11: =TEXT(Table1[[#This Row],[Order Date]],"DDDD") -> Wednesday | V11: Cancelled | W11: =COUNTIF(M2:M251,"Cancelled") -> 18
A12: ORD1011 | B12: 45676 | C12: 45682 | D12: North | E12: Chandigarh | F12: Simran Kaur | G12: Clothing | H12: Denim Jacket | I12: 2 | J12: 2999 | K12: 0.2 | L12: UPI | M12: Delivered | N12: =Table1[[#This Row],[Quantity]]*Table1[[#This Row],[Unit Price (₹)]]*(1-Table1[[#This Row],[Discount %]]) -> 4798.4 | O12: =TEXT(Table1[[#This Row],[Order Date]],"mmmm") -> January | P12: =IF(Table1[[#This Row],[Revenue (₹) ← add]]>=15000,"High Value",IF(Table1[[#This Row],[Revenue (₹) ← add]]>=5000,"Medium","Low")) -> Low | Q12: =VLOOKUP(Table1[[#This Row],[Product]],Table2[],4,FALSE) -> 1700 | R12: =Table1[[#This Row],[Revenue (₹) ← add]]-Table1[[#This Row],[Cost Price ← add]] -> 3098.4 | S12: =IF(C12="", "",Table1[[#This Row],[Delivery Date]]-Table1[[#This Row],[Order Date]]) -> 6 | T12: =TEXT(Table1[[#This Row],[Order Date]],"DDDD") -> Sunday | V12: Revenue in West | W12: =SUMIF(D2:D251,"West",N2:N251) -> 506758.85
A13: ORD1012 | B13: 45676 | C13: 45681 | D13: South | E13: Hyderabad | F13: Karthik Iyer | G13: Electronics | H13: Wireless Mouse | I13: 3 | J13: 799 | K13: 0.15 | L13: UPI | M13: Delivered | N13: =Table1[[#This Row],[Quantity]]*Table1[[#This Row],[Unit Price (₹)]]*(1-Table1[[#This Row],[Discount %]]) -> 2037.45 | O13: =TEXT(Table1[[#This Row],[Order Date]],"mmmm") -> January | P13: =IF(Table1[[#This Row],[Revenue (₹) ← add]]>=15000,"High Value",IF(Table1[[#This Row],[Revenue (₹) ← add]]>=5000,"Medium","Low")) -> Low | Q13: =VLOOKUP(Table1[[#This Row],[Product]],Table2[],4,FALSE) -> 450 | R13: =Table1[[#This Row],[Revenue (₹) ← add]]-Table1[[#This Row],[Cost Price ← add]] -> 1587.45 | S13: =IF(C13="", "",Table1[[#This Row],[Delivery Date]]-Table1[[#This Row],[Order Date]]) -> 5 | T13: =TEXT(Table1[[#This Row],[Order Date]],"DDDD") -> Sunday | V13: Revenue by Delievered only prod | W13: =SUMIF(M2:M251,"Delivered",N2:N251) -> 1526078.9
A14: ORD1013 | B14: 45678 | C14: 45683 | D14: East | E14: Kolkata | F14: Rohit Das | G14: Stationery | H14: Desk Organizer | I14: 6 | J14: 599 | K14: 0 | L14: COD | M14: Delivered | N14: =Table1[[#This Row],[Quantity]]*Table1[[#This Row],[Unit Price (₹)]]*(1-Table1[[#This Row],[Discount %]]) -> 3594 | O14: =TEXT(Table1[[#This Row],[Order Date]],"mmmm") -> January | P14: =IF(Table1[[#This Row],[Revenue (₹) ← add]]>=15000,"High Value",IF(Table1[[#This Row],[Revenue (₹) ← add]]>=5000,"Medium","Low")) -> Low | Q14: =VLOOKUP(Table1[[#This Row],[Product]],Table2[],4,FALSE) -> 320 | R14: =Table1[[#This Row],[Revenue (₹) ← add]]-Table1[[#This Row],[Cost Price ← add]] -> 3274 | S14: =IF(C14="", "",Table1[[#This Row],[Delivery Date]]-Table1[[#This Row],[Order Date]]) -> 5 | T14: =TEXT(Table1[[#This Row],[Order Date]],"DDDD") -> Tuesday | V14: Orders placed in March | W14: =COUNTIF(O2:O227,"March") -> 15
A15: ORD1014 | B15: 45678 | C15: 45681 | D15: South | E15: Chennai | F15: Meera Nair | G15: Electronics | H15: Bluetooth Speaker | I15: 4 | J15: 2499 | K15: 0.2 | L15: COD | M15: Delivered | N15: =Table1[[#This Row],[Quantity]]*Table1[[#This Row],[Unit Price (₹)]]*(1-Table1[[#This Row],[Discount %]]) -> 7996.8 | O15: =TEXT(Table1[[#This Row],[Order Date]],"mmmm") -> January | P15: =IF(Table1[[#This Row],[Revenue (₹) ← add]]>=15000,"High Value",IF(Table1[[#This Row],[Revenue (₹) ← add]]>=5000,"Medium","Low")) -> Medium | Q15: =VLOOKUP(Table1[[#This Row],[Product]],Table2[],4,FALSE) -> 1500 | R15: =Table1[[#This Row],[Revenue (₹) ← add]]-Table1[[#This Row],[Cost Price ← add]] -> 6496.8 | S15: =IF(C15="", "",Table1[[#This Row],[Delivery Date]]-Table1[[#This Row],[Order Date]]) -> 3 | T15: =TEXT(Table1[[#This Row],[Order Date]],"DDDD") -> Tuesday | V15: Revenue from Electronics in North | W15: =SUMIFS(N2:N251,G2:G251,"Electronics",M2:M251,"Delivered") -> 396617.05
A16: ORD1015 | B16: 45678 | C16: 45685 | D16: West | E16: Ahmedabad | F16: Neha Joshi | G16: Electronics | H16: Bluetooth Speaker | I16: 2 | J16: 2499 | K16: 0.05 | L16: Credit Card | M16: Returned | N16: =Table1[[#This Row],[Quantity]]*Table1[[#This Row],[Unit Price (₹)]]*(1-Table1[[#This Row],[Discount %]]) -> 4748.1 | O16: =TEXT(Table1[[#This Row],[Order Date]],"mmmm") -> January | P16: =IF(Table1[[#This Row],[Revenue (₹) ← add]]>=15000,"High Value",IF(Table1[[#This Row],[Revenue (₹) ← add]]>=5000,"Medium","Low")) -> Low | Q16: =VLOOKUP(Table1[[#This Row],[Product]],Table2[],4,FALSE) -> 1500 | R16: =Table1[[#This Row],[Revenue (₹) ← add]]-Table1[[#This Row],[Cost Price ← add]] -> 3248.1 | S16: =IF(C16="", "",Table1[[#This Row],[Delivery Date]]-Table1[[#This Row],[Order Date]]) -> 7 | T16: =TEXT(Table1[[#This Row],[Order Date]],"DDDD") -> Tuesday | V16: Average discount on upi | W16: =AVERAGEIF(L2:L251,"UPI",K2:K251) -> 0.089204545
A17: ORD1016 | B17: 45679 | C17: 45685 | D17: East | E17: Bhubaneswar | F17: Ananya Sen | G17: Clothing | H17: Cotton T-Shirt | I17: 8 | J17: 599 | K17: 0 | L17: UPI | M17: Delivered | N17: =Table1[[#This Row],[Quantity]]*Table1[[#This Row],[Unit Price (₹)]]*(1-Table1[[#This Row],[Discount %]]) -> 4792 | O17: =TEXT(Table1[[#This Row],[Order Date]],"mmmm") -> January | P17: =IF(Table1[[#This Row],[Revenue (₹) ← add]]>=15000,"High Value",IF(Table1[[#This Row],[Revenue (₹) ← add]]>=5000,"Medium","Low")) -> Low | Q17: =VLOOKUP(Table1[[#This Row],[Product]],Table2[],4,FALSE) -> 300 | R17: =Table1[[#This Row],[Revenue (₹) ← add]]-Table1[[#This Row],[Cost Price ← add]] -> 4492 | S17: =IF(C17="", "",Table1[[#This Row],[Delivery Date]]-Table1[[#This Row],[Order Date]]) -> 6 | T17: =TEXT(Table1[[#This Row],[Order Date]],"DDDD") -> Wednesday | V17: average Discount on upi and cod | W17: =AVERAGEIF(L2:L251,"COD",K2:K251) -> 0.082954545
A18: ORD1017 | B18: 45682 | C18: 45685 | D18: West | E18: Pune | F18: Vikram Shah | G18: Clothing | H18: Cotton T-Shirt | I18: 2 | J18: 599 | K18: 0.2 | L18: COD | M18: Delivered | N18: =Table1[[#This Row],[Quantity]]*Table1[[#This Row],[Unit Price (₹)]]*(1-Table1[[#This Row],[Discount %]]) -> 958.4 | O18: =TEXT(Table1[[#This Row],[Order Date]],"mmmm") -> January | P18: =IF(Table1[[#This Row],[Revenue (₹) ← add]]>=15000,"High Value",IF(Table1[[#This Row],[Revenue (₹) ← add]]>=5000,"Medium","Low")) -> Low | Q18: =VLOOKUP(Table1[[#This Row],[Product]],Table2[],4,FALSE) -> 300 | R18: =Table1[[#This Row],[Revenue (₹) ← add]]-Table1[[#This Row],[Cost Price ← add]] -> 658.4 | S18: =IF(C18="", "",Table1[[#This Row],[Delivery Date]]-Table1[[#This Row],[Order Date]]) -> 3 | T18: =TEXT(Table1[[#This Row],[Order Date]],"DDDD") -> Saturday | V18: Using Filter avg discount on upi+cod | W18: {=AVERAGE(_xlfn._xlws.FILTER(K2:K251,(L2:L251="COD")+(L2:L251="UPI")))} -> 0.087121212
A19: ORD1018 | B19: 45683 | C19: 45690 | D19: West | E19: Ahmedabad | F19: Neha Joshi | G19: Clothing | H19: Cotton T-Shirt | I19: 4 | J19: 599 | K19: 0.05 | L19: UPI | M19: Delivered | N19: =Table1[[#This Row],[Quantity]]*Table1[[#This Row],[Unit Price (₹)]]*(1-Table1[[#This Row],[Discount %]]) -> 2276.2 | O19: =TEXT(Table1[[#This Row],[Order Date]],"mmmm") -> January | P19: =IF(Table1[[#This Row],[Revenue (₹) ← add]]>=15000,"High Value",IF(Table1[[#This Row],[Revenue (₹) ← add]]>=5000,"Medium","Low")) -> Low | Q19: =VLOOKUP(Table1[[#This Row],[Product]],Table2[],4,FALSE) -> 300 | R19: =Table1[[#This Row],[Revenue (₹) ← add]]-Table1[[#This Row],[Cost Price ← add]] -> 1976.2 | S19: =IF(C19="", "",Table1[[#This Row],[Delivery Date]]-Table1[[#This Row],[Order Date]]) -> 7 | T19: =TEXT(Table1[[#This Row],[Order Date]],"DDDD") -> Sunday
A20: ORD1019 | B20: 45685 | C20: 45694 | D20: East | E20: Kolkata | F20: Ananya Sen | G20: Stationery | H20: Notebook Pack | I20: 8 | J20: 349 | K20: 0.15 | L20: Net Banking | M20: Delivered | N20: =Table1[[#This Row],[Quantity]]*Table1[[#This Row],[Unit Price (₹)]]*(1-Table1[[#This Row],[Discount %]]) -> 2373.2 | O20: =TEXT(Table1[[#This Row],[Order Date]],"mmmm") -> January | P20: =IF(Table1[[#This Row],[Revenue (₹) ← add]]>=15000,"High Value",IF(Table1[[#This Row],[Revenue (₹) ← add]]>=5000,"Medium","Low")) -> Low | Q20: =VLOOKUP(Table1[[#This Row],[Product]],Table2[],4,FALSE) -> 180 | R20: =Table1[[#This Row],[Revenue (₹) ← add]]-Table1[[#This Row],[Cost Price ← add]] -> 2193.2 | S20: =IF(C20="", "",Table1[[#This Row],[Delivery Date]]-Table1[[#This Row],[Order Date]]) -> 9 | T20: =TEXT(Table1[[#This Row],[Order Date]],"DDDD") -> Tuesday | V20: Which Order ID has the highest revenue? | W20: =_xlfn.XLOOKUP(MAX(Table1[Revenue (₹) ← add]),Table1[Revenue (₹) ← add],Table1[Order ID],0,0,-1) -> ORD1222
A21: ORD1020 | B21: 45685 | C21: 45692 | D21: North | E21: Delhi | F21: Aarav Mehta | G21: Furniture | H21: Bookshelf | I21: 2 | J21: 5499 | K21: 0.2 | L21: UPI | M21: Delivered | N21: =Table1[[#This Row],[Quantity]]*Table1[[#This Row],[Unit Price (₹)]]*(1-Table1[[#This Row],[Discount %]]) -> 8798.4 | O21: =TEXT(Table1[[#This Row],[Order Date]],"mmmm") -> January | P21: =IF(Table1[[#This Row],[Revenue (₹) ← add]]>=15000,"High Value",IF(Table1[[#This Row],[Revenue (₹) ← add]]>=5000,"Medium","Low")) -> Medium | Q21: =VLOOKUP(Table1[[#This Row],[Product]],Table2[],4,FALSE) -> 3300 | R21: =Table1[[#This Row],[Revenue (₹) ← add]]-Table1[[#This Row],[Cost Price ← add]] -> 5498.4 | S21: =IF(C21="", "",Table1[[#This Row],[Delivery Date]]-Table1[[#This Row],[Order Date]]) -> 7 | T21: =TEXT(Table1[[#This Row],[Order Date]],"DDDD") -> Tuesday | V21: Filter | W21: {=_xlfn._xlws.FILTER(Table1[Order ID],N2:N251=(MAX(N2:N251)))} -> ORD1222
A22: ORD1021 | B22: 45687 | C22: 45695 | D22: North | E22: Delhi | F22: Aarav Mehta | G22: Stationery | H22: Desk Organizer | I22: 7 | J22: 599 | K22: 0 | L22: Net Banking | M22: Delivered | N22: =Table1[[#This Row],[Quantity]]*Table1[[#This Row],[Unit Price (₹)]]*(1-Table1[[#This Row],[Discount %]]) -> 4193 | O22: =TEXT(Table1[[#This Row],[Order Date]],"mmmm") -> January | P22: =IF(Table1[[#This Row],[Revenue (₹) ← add]]>=15000,"High Value",IF(Table1[[#This Row],[Revenue (₹) ← add]]>=5000,"Medium","Low")) -> Low | Q22: =VLOOKUP(Table1[[#This Row],[Product]],Table2[],4,FALSE) -> 320 | R22: =Table1[[#This Row],[Revenue (₹) ← add]]-Table1[[#This Row],[Cost Price ← add]] -> 3873 | S22: =IF(C22="", "",Table1[[#This Row],[Delivery Date]]-Table1[[#This Row],[Order Date]]) -> 8 | T22: =TEXT(Table1[[#This Row],[Order Date]],"DDDD") -> Thursday | W22: =INDEX(Table1[Order ID],MATCH(MAX(Table1[Revenue (₹) ← add]), Table1[Revenue (₹) ← add],0)) -> ORD1222
A23: ORD1022 | B23: 45691 | C23: 45700 | D23: West | E23: Ahmedabad | F23: Vikram Shah | G23: Stationery | H23: Desk Organizer | I23: 4 | J23: 599 | K23: 0 | L23: UPI | M23: Returned | N23: =Table1[[#This Row],[Quantity]]*Table1[[#This Row],[Unit Price (₹)]]*(1-Table1[[#This Row],[Discount %]]) -> 2396 | O23: =TEXT(Table1[[#This Row],[Order Date]],"mmmm") -> February | P23: =IF(Table1[[#This Row],[Revenue (₹) ← add]]>=15000,"High Value",IF(Table1[[#This Row],[Revenue (₹) ← add]]>=5000,"Medium","Low")) -> Low | Q23: =VLOOKUP(Table1[[#This Row],[Product]],Table2[],4,FALSE) -> 320 | R23: =Table1[[#This Row],[Revenue (₹) ← add]]-Table1[[#This Row],[Cost Price ← add]] -> 2076 | S23: =IF(C23="", "",Table1[[#This Row],[Delivery Date]]-Table1[[#This Row],[Order Date]]) -> 9 | T23: =TEXT(Table1[[#This Row],[Order Date]],"DDDD") -> Monday | W23: =COUNTIF(N2:N251,MAX(N2:N251)) -> 1
A24: ORD1023 | B24: 45694 | C24: 45703 | D24: West | E24: Mumbai | F24: Vikram Shah | G24: Electronics | H24: Headphones | I24: 5 | J24: 1999 | K24: 0.15 | L24: Credit Card | M24: Delivered | N24: =Table1[[#This Row],[Quantity]]*Table1[[#This Row],[Unit Price (₹)]]*(1-Table1[[#This Row],[Discount %]]) -> 8495.75 | O24: =TEXT(Table1[[#This Row],[Order Date]],"mmmm") -> February | P24: =IF(Table1[[#This Row],[Revenue (₹) ← add]]>=15000,"High Value",IF(Table1[[#This Row],[Revenue (₹) ← add]]>=5000,"Medium","Low")) -> Medium | Q24: =VLOOKUP(Table1[[#This Row],[Product]],Table2[],4,FALSE) -> 1100 | R24: =Table1[[#This Row],[Revenue (₹) ← add]]-Table1[[#This Row],[Cost Price ← add]] -> 7395.75 | S24: =IF(C24="", "",Table1[[#This Row],[Delivery Date]]-Table1[[#This Row],[Order Date]]) -> 9 | T24: =TEXT(Table1[[#This Row],[Order Date]],"DDDD") -> Thursday | V24: How many orders had discount ≥ 10% AND quantity > 5? | W24: =COUNTIFS(Table1[Discount %],">-10%",Table1[Quantity],">5") -> 79
A25: ORD1024 | B25: 45695 | C25: 45704 | D25: West | E25: Pune | F25: Neha Joshi | G25: Electronics | H25: Wireless Mouse | I25: 3 | J25: 799 | K25: 0.05 | L25: Debit Card | M25: Delivered | N25: =Table1[[#This Row],[Quantity]]*Table1[[#This Row],[Unit Price (₹)]]*(1-Table1[[#This Row],[Discount %]]) -> 2277.15 | O25: =TEXT(Table1[[#This Row],[Order Date]],"mmmm") -> February | P25: =IF(Table1[[#This Row],[Revenue (₹) ← add]]>=15000,"High Value",IF(Table1[[#This Row],[Revenue (₹) ← add]]>=5000,"Medium","Low")) -> Low | Q25: =VLOOKUP(Table1[[#This Row],[Product]],Table2[],4,FALSE) -> 450 | R25: =Table1[[#This Row],[Revenue (₹) ← add]]-Table1[[#This Row],[Cost Price ← add]] -> 1827.15 | S25: =IF(C25="", "",Table1[[#This Row],[Delivery Date]]-Table1[[#This Row],[Order Date]]) -> 9 | T25: =TEXT(Table1[[#This Row],[Order Date]],"DDDD") -> Friday | V25: What is the return rate (%) for Clothing? Returned orders ÷ all orders in that category. | W25: =(COUNTIFS(Table1[Status],"Returned",Table1[Category],"Clothing"))/COUNTIF(Table1[Category],"Clothing") -> 0.038461538
A26: ORD1025 | B26: 45695 | C26: 45704 | D26: South | E26: Hyderabad | F26: Meera Nair | G26: Electronics | H26: Power Bank | I26: 2 | J26: 1499 | K26: 0.05 | L26: UPI | M26: Delivered | N26: =Table1[[#This Row],[Quantity]]*Table1[[#This Row],[Unit Price (₹)]]*(1-Table1[[#This Row],[Discount %]]) -> 2848.1 | O26: =TEXT(Table1[[#This Row],[Order Date]],"mmmm") -> February | P26: =IF(Table1[[#This Row],[Revenue (₹) ← add]]>=15000,"High Value",IF(Table1[[#This Row],[Revenue (₹) ← add]]>=5000,"Medium","Low")) -> Low | Q26: =VLOOKUP(Table1[[#This Row],[Product]],Table2[],4,FALSE) -> 850 | R26: =Table1[[#This Row],[Revenue (₹) ← add]]-Table1[[#This Row],[Cost Price ← add]] -> 1998.1 | S26: =IF(C26="", "",Table1[[#This Row],[Delivery Date]]-Table1[[#This Row],[Order Date]]) -> 9 | T26: =TEXT(Table1[[#This Row],[Order Date]],"DDDD") -> Friday | V26: How many orders were placed on a weekend?
A27: ORD1026 | B27: 45695 | C27: 45701 | D27: North | E27: Lucknow | F27: Aarav Mehta | G27: Clothing | H27: Cotton T-Shirt | I27: 3 | J27: 599 | K27: 0.2 | L27: Net Banking | M27: Delivered | N27: =Table1[[#This Row],[Quantity]]*Table1[[#This Row],[Unit Price (₹)]]*(1-Table1[[#This Row],[Discount %]]) -> 1437.6 | O27: =TEXT(Table1[[#This Row],[Order Date]],"mmmm") -> February | P27: =IF(Table1[[#This Row],[Revenue (₹) ← add]]>=15000,"High Value",IF(Table1[[#This Row],[Revenue (₹) ← add]]>=5000,"Medium","Low")) -> Low | Q27: =VLOOKUP(Table1[[#This Row],[Product]],Table2[],4,FALSE) -> 300 | R27: =Table1[[#This Row],[Revenue (₹) ← add]]-Table1[[#This Row],[Cost Price ← add]] -> 1137.6 | S27: =IF(C27="", "",Table1[[#This Row],[Delivery Date]]-Table1[[#This Row],[Order Date]]) -> 6 | T27: =TEXT(Table1[[#This Row],[Order Date]],"DDDD") -> Friday | W27: {=SUMPRODUCT(--(WEEKDAY(C2:C251,2)=7))+SUMPRODUCT(--(WEEKDAY(C2:C251,2)=7))} -> 92
A28: ORD1027 | B28: 45698 | C28: 45705 | D28: East | E28: Bhubaneswar | F28: Rohit Das | G28: Stationery | H28: Desk Organizer | I28: 15 | J28: 599 | K28: 0 | L28: UPI | M28: Delivered | N28: =Table1[[#This Row],[Quantity]]*Table1[[#This Row],[Unit Price (₹)]]*(1-Table1[[#This Row],[Discount %]]) -> 8985 | O28: =TEXT(Table1[[#This Row],[Order Date]],"mmmm") -> February | P28: =IF(Table1[[#This Row],[Revenue (₹) ← add]]>=15000,"High Value",IF(Table1[[#This Row],[Revenue (₹) ← add]]>=5000,"Medium","Low")) -> Medium | Q28: =VLOOKUP(Table1[[#This Row],[Product]],Table2[],4,FALSE) -> 320 | R28: =Table1[[#This Row],[Revenue (₹) ← add]]-Table1[[#This Row],[Cost Price ← add]] -> 8665 | S28: =IF(C28="", "",Table1[[#This Row],[Delivery Date]]-Table1[[#This Row],[Order Date]]) -> 7 | T28: =TEXT(Table1[[#This Row],[Order Date]],"DDDD") -> Monday | V28: Average delievery day sin the west region | W28: =AVERAGEIF(Table1[Region],"West",Table1[Delivery Days ← add]) -> 5.9666667
A29: ORD1028 | B29: 45698 | C29: 45704 | D29: West | E29: Mumbai | F29: Neha Joshi | G29: Furniture | H29: Bookshelf | I29: 3 | J29: 5499 | K29: 0.05 | L29: UPI | M29: Delivered | N29: =Table1[[#This Row],[Quantity]]*Table1[[#This Row],[Unit Price (₹)]]*(1-Table1[[#This Row],[Discount %]]) -> 15672.15 | O29: =TEXT(Table1[[#This Row],[Order Date]],"mmmm") -> February | P29: =IF(Table1[[#This Row],[Revenue (₹) ← add]]>=15000,"High Value",IF(Table1[[#This Row],[Revenue (₹) ← add]]>=5000,"Medium","Low")) -> High Value | Q29: =VLOOKUP(Table1[[#This Row],[Product]],Table2[],4,FALSE) -> 3300 | R29: =Table1[[#This Row],[Revenue (₹) ← add]]-Table1[[#This Row],[Cost Price ← add]] -> 12372.15 | S29: =IF(C29="", "",Table1[[#This Row],[Delivery Date]]-Table1[[#This Row],[Order Date]]) -> 6 | T29: =TEXT(Table1[[#This Row],[Order Date]],"DDDD") -> Monday
A30: ORD1029 | B30: 45698 | C30: 45704 | D30: South | E30: Bengaluru | F30: Karthik Iyer | G30: Furniture | H30: Bookshelf | I30: 3 | J30: 5499 | K30: 0.2 | L30: Credit Card | M30: Delivered | N30: =Table1[[#This Row],[Quantity]]*Table1[[#This Row],[Unit Price (₹)]]*(1-Table1[[#This Row],[Discount %]]) -> 13197.6 | O30: =TEXT(Table1[[#This Row],[Order Date]],"mmmm") -> February | P30: =IF(Table1[[#This Row],[Revenue (₹) ← add]]>=15000,"High Value",IF(Table1[[#This Row],[Revenue (₹) ← add]]>=5000,"Medium","Low")) -> Medium | Q30: =VLOOKUP(Table1[[#This Row],[Product]],Table2[],4,FALSE) -> 3300 | R30: =Table1[[#This Row],[Revenue (₹) ← add]]-Table1[[#This Row],[Cost Price ← add]] -> 9897.6 | S30: =IF(C30="", "",Table1[[#This Row],[Delivery Date]]-Table1[[#This Row],[Order Date]]) -> 6 | T30: =TEXT(Table1[[#This Row],[Order Date]],"DDDD") -> Monday
A31: ORD1030 | B31: 45699 | C31: 45702 | D31: West | E31: Mumbai | F31: Vikram Shah | G31: Furniture | H31: Study Desk | I31: 3 | J31: 8499 | K31: 0.1 | L31: COD | M31: Delivered | N31: =Table1[[#This Row],[Quantity]]*Table1[[#This Row],[Unit Price (₹)]]*(1-Table1[[#This Row],[Discount %]]) -> 22947.3 | O31: =TEXT(Table1[[#This Row],[Order Date]],"mmmm") -> February | P31: =IF(Table1[[#This Row],[Revenue (₹) ← add]]>=15000,"High Value",IF(Table1[[#This Row],[Revenue (₹) ← add]]>=5000,"Medium","Low")) -> High Value | Q31: =VLOOKUP(Table1[[#This Row],[Product]],Table2[],4,FALSE) -> 5200 | R31: =Table1[[#This Row],[Revenue (₹) ← add]]-Table1[[#This Row],[Cost Price ← add]] -> 17747.3 | S31: =IF(C31="", "",Table1[[#This Row],[Delivery Date]]-Table1[[#This Row],[Order Date]]) -> 3 | T31: =TEXT(Table1[[#This Row],[Order Date]],"DDDD") -> Tuesday
A32: ORD1031 | B32: 45701 | C32: 45706 | D32: North | E32: Lucknow | F32: Simran Kaur | G32: Furniture | H32: Bookshelf | I32: 3 | J32: 5499 | K32: 0.05 | L32: UPI | M32: Delivered | N32: =Table1[[#This Row],[Quantity]]*Table1[[#This Row],[Unit Price (₹)]]*(1-Table1[[#This Row],[Discount %]]) -> 15672.15 | O32: =TEXT(Table1[[#This Row],[Order Date]],"mmmm") -> February | P32: =IF(Table1[[#This Row],[Revenue (₹) ← add]]>=15000,"High Value",IF(Table1[[#This Row],[Revenue (₹) ← add]]>=5000,"Medium","Low")) -> High Value | Q32: =VLOOKUP(Table1[[#This Row],[Product]],Table2[],4,FALSE) -> 3300 | R32: =Table1[[#This Row],[Revenue (₹) ← add]]-Table1[[#This Row],[Cost Price ← add]] -> 12372.15 | S32: =IF(C32="", "",Table1[[#This Row],[Delivery Date]]-Table1[[#This Row],[Order Date]]) -> 5 | T32: =TEXT(Table1[[#This Row],[Order Date]],"DDDD") -> Thursday
A33: ORD1032 | B33: 45704 | C33: 45710 | D33: East | E33: Bhubaneswar | F33: Rohit Das | G33: Furniture | H33: Bookshelf | I33: 3 | J33: 5499 | K33: 0 | L33: Debit Card | M33: Delivered | N33: =Table1[[#This Row],[Quantity]]*Table1[[#This Row],[Unit Price (₹)]]*(1-Table1[[#This Row],[Discount %]]) -> 16497 | O33: =TEXT(Table1[[#This Row],[Order Date]],"mmmm") -> February | P33: =IF(Table1[[#This Row],[Revenue (₹) ← add]]>=15000,"High Value",IF(Table1[[#This Row],[Revenue (₹) ← add]]>=5000,"Medium","Low")) -> High Value | Q33: =VLOOKUP(Table1[[#This Row],[Product]],Table2[],4,FALSE) -> 3300 | R33: =Table1[[#This Row],[Revenue (₹) ← add]]-Table1[[#This Row],[Cost Price ← add]] -> 13197 | S33: =IF(C33="", "",Table1[[#This Row],[Delivery Date]]-Table1[[#This Row],[Order Date]]) -> 6 | T33: =TEXT(Table1[[#This Row],[Order Date]],"DDDD") -> Sunday
A34: ORD1033 | B34: 45709 | C34: 45717 | D34: North | E34: Lucknow | F34: Simran Kaur | G34: Furniture | H34: Study Desk | I34: 3 | J34: 8499 | K34: 0.1 | L34: COD | M34: Delivered | N34: =Table1[[#This Row],[Quantity]]*Table1[[#This Row],[Unit Price (₹)]]*(1-Table1[[#This Row],[Discount %]]) -> 22947.3 | O34: =TEXT(Table1[[#This Row],[Order Date]],"mmmm") -> February | P34: =IF(Table1[[#This Row],[Revenue (₹) ← add]]>=15000,"High Value",IF(Table1[[#This Row],[Revenue (₹) ← add]]>=5000,"Medium","Low")) -> High Value | Q34: =VLOOKUP(Table1[[#This Row],[Product]],Table2[],4,FALSE) -> 5200 | R34: =Table1[[#This Row],[Revenue (₹) ← add]]-Table1[[#This Row],[Cost Price ← add]] -> 17747.3 | S34: =IF(C34="", "",Table1[[#This Row],[Delivery Date]]-Table1[[#This Row],[Order Date]]) -> 8 | T34: =TEXT(Table1[[#This Row],[Order Date]],"DDDD") -> Friday
A35: ORD1034 | B35: 45711 | C35: 45717 | D35: East | E35: Kolkata | F35: Rohit Das | G35: Furniture | H35: Study Desk | I35: 2 | J35: 8499 | K35: 0.05 | L35: Credit Card | M35: Delivered | N35: =Table1[[#This Row],[Quantity]]*Table1[[#This Row],[Unit Price (₹)]]*(1-Table1[[#This Row],[Discount %]]) -> 16148.1 | O35: =TEXT(Table1[[#This Row],[Order Date]],"mmmm") -> February | P35: =IF(Table1[[#This Row],[Revenue (₹) ← add]]>=15000,"High Value",IF(Table1[[#This Row],[Revenue (₹) ← add]]>=5000,"Medium","Low")) -> High Value | Q35: =VLOOKUP(Table1[[#This Row],[Product]],Table2[],4,FALSE) -> 5200 | R35: =Table1[[#This Row],[Revenue (₹) ← add]]-Table1[[#This Row],[Cost Price ← add]] -> 10948.1 | S35: =IF(C35="", "",Table1[[#This Row],[Delivery Date]]-Table1[[#This Row],[Order Date]]) -> 6 | T35: =TEXT(Table1[[#This Row],[Order Date]],"DDDD") -> Sunday
A36: ORD1035 | B36: 45711 | C36: 45714 | D36: South | E36: Chennai | F36: Meera Nair | G36: Stationery | H36: Gel Pen Box | I36: 22 | J36: 249 | K36: 0.15 | L36: UPI | M36: Delivered | N36: =Table1[[#This Row],[Quantity]]*Table1[[#This Row],[Unit Price (₹)]]*(1-Table1[[#This Row],[Discount %]]) -> 4656.3 | O36: =TEXT(Table1[[#This Row],[Order Date]],"mmmm") -> February | P36: =IF(Table1[[#This Row],[Revenue (₹) ← add]]>=15000,"High Value",IF(Table1[[#This Row],[Revenue (₹) ← add]]>=5000,"Medium","Low")) -> Low | Q36: =VLOOKUP(Table1[[#This Row],[Product]],Table2[],4,FALSE) -> 120 | R36: =Table1[[#This Row],[Revenue (₹) ← add]]-Table1[[#This Row],[Cost Price ← add]] -> 4536.3 | S36: =IF(C36="", "",Table1[[#This Row],[Delivery Date]]-Table1[[#This Row],[Order Date]]) -> 3 | T36: =TEXT(Table1[[#This Row],[Order Date]],"DDDD") -> Sunday
A37: ORD1036 | B37: 45713 | C37: 45722 | D37: South | E37: Bengaluru | F37: Karthik Iyer | G37: Clothing | H37: Cotton T-Shirt | I37: 4 | J37: 599 | K37: 0.05 | L37: UPI | M37: Delivered | N37: =Table1[[#This Row],[Quantity]]*Table1[[#This Row],[Unit Price (₹)]]*(1-Table1[[#This Row],[Discount %]]) -> 2276.2 | O37: =TEXT(Table1[[#This Row],[Order Date]],"mmmm") -> February | P37: =IF(Table1[[#This Row],[Revenue (₹) ← add]]>=15000,"High Value",IF(Table1[[#This Row],[Revenue (₹) ← add]]>=5000,"Medium","Low")) -> Low | Q37: =VLOOKUP(Table1[[#This Row],[Product]],Table2[],4,FALSE) -> 300 | R37: =Table1[[#This Row],[Revenue (₹) ← add]]-Table1[[#This Row],[Cost Price ← add]] -> 1976.2 | S37: =IF(C37="", "",Table1[[#This Row],[Delivery Date]]-Table1[[#This Row],[Order Date]]) -> 9 | T37: =TEXT(Table1[[#This Row],[Order Date]],"DDDD") -> Tuesday
A38: ORD1037 | B38: 45717 | C38: 45722 | D38: South | E38: Bengaluru | F38: Karthik Iyer | G38: Electronics | H38: Power Bank | I38: 1 | J38: 1499 | K38: 0.2 | L38: UPI | M38: Delivered | N38: =Table1[[#This Row],[Quantity]]*Table1[[#This Row],[Unit Price (₹)]]*(1-Table1[[#This Row],[Discount %]]) -> 1199.2 | O38: =TEXT(Table1[[#This Row],[Order Date]],"mmmm") -> March | P38: =IF(Table1[[#This Row],[Revenue (₹) ← add]]>=15000,"High Value",IF(Table1[[#This Row],[Revenue (₹) ← add]]>=5000,"Medium","Low")) -> Low | Q38: =VLOOKUP(Table1[[#This Row],[Product]],Table2[],4,FALSE) -> 850 | R38: =Table1[[#This Row],[Revenue (₹) ← add]]-Table1[[#This Row],[Cost Price ← add]] -> 349.2 | S38: =IF(C38="", "",Table1[[#This Row],[Delivery Date]]-Table1[[#This Row],[Order Date]]) -> 5 | T38: =TEXT(Table1[[#This Row],[Order Date]],"DDDD") -> Saturday
A39: ORD1038 | B39: 45718 | C39: 45727 | D39: West | E39: Ahmedabad | F39: Neha Joshi | G39: Clothing | H39: Denim Jacket | I39: 2 | J39: 2999 | K39: 0 | L39: Credit Card | M39: Delivered | N39: =Table1[[#This Row],[Quantity]]*Table1[[#This Row],[Unit Price (₹)]]*(1-Table1[[#This Row],[Discount %]]) -> 5998 | O39: =TEXT(Table1[[#This Row],[Order Date]],"mmmm") -> March | P39: =IF(Table1[[#This Row],[Revenue (₹) ← add]]>=15000,"High Value",IF(Table1[[#This Row],[Revenue (₹) ← add]]>=5000,"Medium","Low")) -> Medium | Q39: =VLOOKUP(Table1[[#This Row],[Product]],Table2[],4,FALSE) -> 1700 | R39: =Table1[[#This Row],[Revenue (₹) ← add]]-Table1[[#This Row],[Cost Price ← add]] -> 4298 | S39: =IF(C39="", "",Table1[[#This Row],[Delivery Date]]-Table1[[#This Row],[Order Date]]) -> 9 | T39: =TEXT(Table1[[#This Row],[Order Date]],"DDDD") -> Sunday
A40: ORD1039 | B40: 45719 | C40: 45725 | D40: South | E40: Hyderabad | F40: Karthik Iyer | G40: Stationery | H40: Desk Organizer | I40: 8 | J40: 599 | K40: 0.2 | L40: UPI | M40: Returned | N40: =Table1[[#This Row],[Quantity]]*Table1[[#This Row],[Unit Price (₹)]]*(1-Table1[[#This Row],[Discount %]]) -> 3833.6 | O40: =TEXT(Table1[[#This Row],[Order Date]],"mmmm") -> March | P40: =IF(Table1[[#This Row],[Revenue (₹) ← add]]>=15000,"High Value",IF(Table1[[#This Row],[Revenue (₹) ← add]]>=5000,"Medium","Low")) -> Low | Q40: =VLOOKUP(Table1[[#This Row],[Product]],Table2[],4,FALSE) -> 320 | R40: =Table1[[#This Row],[Revenue (₹) ← add]]-Table1[[#This Row],[Cost Price ← add]] -> 3513.6 | S40: =IF(C40="", "",Table1[[#This Row],[Delivery Date]]-Table1[[#This Row],[Order Date]]) -> 6 | T40: =TEXT(Table1[[#This Row],[Order Date]],"DDDD") -> Monday
A41: ORD1040 | B41: 45720 | C41: 45729 | D41: East | E41: Kolkata | F41: Rohit Das | G41: Stationery | H41: Desk Organizer | I41: 14 | J41: 599 | K41: 0 | L41: COD | M41: Delivered | N41: =Table1[[#This Row],[Quantity]]*Table1[[#This Row],[Unit Price (₹)]]*(1-Table1[[#This Row],[Discount %]]) -> 8386 | O41: =TEXT(Table1[[#This Row],[Order Date]],"mmmm") -> March | P41: =IF(Table1[[#This Row],[Revenue (₹) ← add]]>=15000,"High Value",IF(Table1[[#This Row],[Revenue (₹) ← add]]>=5000,"Medium","Low")) -> Medium | Q41: =VLOOKUP(Table1[[#This Row],[Product]],Table2[],4,FALSE) -> 320 | R41: =Table1[[#This Row],[Revenue (₹) ← add]]-Table1[[#This Row],[Cost Price ← add]] -> 8066 | S41: =IF(C41="", "",Table1[[#This Row],[Delivery Date]]-Table1[[#This Row],[Order Date]]) -> 9 | T41: =TEXT(Table1[[#This Row],[Order Date]],"DDDD") -> Tuesday
A42: ORD1041 | B42: 45720 | D42: South | E42: Hyderabad | F42: Karthik Iyer | G42: Electronics | H42: Wireless Mouse | I42: 6 | J42: 799 | K42: 0.15 | L42: Debit Card | M42: Cancelled | N42: =Table1[[#This Row],[Quantity]]*Table1[[#This Row],[Unit Price (₹)]]*(1-Table1[[#This Row],[Discount %]]) -> 4074.9 | O42: =TEXT(Table1[[#This Row],[Order Date]],"mmmm") -> March | P42: =IF(Table1[[#This Row],[Revenue (₹) ← add]]>=15000,"High Value",IF(Table1[[#This Row],[Revenue (₹) ← add]]>=5000,"Medium","Low")) -> Low | Q42: =VLOOKUP(Table1[[#This Row],[Product]],Table2[],4,FALSE) -> 450 | R42: =Table1[[#This Row],[Revenue (₹) ← add]]-Table1[[#This Row],[Cost Price ← add]] -> 3624.9 | S42: =IF(C42="", "",Table1[[#This Row],[Delivery Date]]-Table1[[#This Row],[Order Date]]) | T42: =TEXT(Table1[[#This Row],[Order Date]],"DDDD") -> Tuesday
A43: ORD1042 | B43: 45725 | C43: 45727 | D43: West | E43: Mumbai | F43: Neha Joshi | G43: Stationery | H43: Gel Pen Box | I43: 6 | J43: 249 | K43: 0 | L43: Net Banking | M43: Delivered | N43: =Table1[[#This Row],[Quantity]]*Table1[[#This Row],[Unit Price (₹)]]*(1-Table1[[#This Row],[Discount %]]) -> 1494 | O43: =TEXT(Table1[[#This Row],[Order Date]],"mmmm") -> March | P43: =IF(Table1[[#This Row],[Revenue (₹) ← add]]>=15000,"High Value",IF(Table1[[#This Row],[Revenue (₹) ← add]]>=5000,"Medium","Low")) -> Low | Q43: =VLOOKUP(Table1[[#This Row],[Product]],Table2[],4,FALSE) -> 120 | R43: =Table1[[#This Row],[Revenue (₹) ← add]]-Table1[[#This Row],[Cost Price ← add]] -> 1374 | S43: =IF(C43="", "",Table1[[#This Row],[Delivery Date]]-Table1[[#This Row],[Order Date]]) -> 2 | T43: =TEXT(Table1[[#This Row],[Order Date]],"DDDD") -> Sunday
A44: ORD1043 | B44: 45725 | C44: 45734 | D44: East | E44: Patna | F44: Ananya Sen | G44: Stationery | H44: Notebook Pack | I44: 7 | J44: 349 | K44: 0.1 | L44: UPI | M44: Delivered | N44: =Table1[[#This Row],[Quantity]]*Table1[[#This Row],[Unit Price (₹)]]*(1-Table1[[#This Row],[Discount %]]) -> 2198.7 | O44: =TEXT(Table1[[#This Row],[Order Date]],"mmmm") -> March | P44: =IF(Table1[[#This Row],[Revenue (₹) ← add]]>=15000,"High Value",IF(Table1[[#This Row],[Revenue (₹) ← add]]>=5000,"Medium","Low")) -> Low | Q44: =VLOOKUP(Table1[[#This Row],[Product]],Table2[],4,FALSE) -> 180 | R44: =Table1[[#This Row],[Revenue (₹) ← add]]-Table1[[#This Row],[Cost Price ← add]] -> 2018.7 | S44: =IF(C44="", "",Table1[[#This Row],[Delivery Date]]-Table1[[#This Row],[Order Date]]) -> 9 | T44: =TEXT(Table1[[#This Row],[Order Date]],"DDDD") -> Sunday
A45: ORD1044 | B45: 45727 | C45: 45733 | D45: North | E45: Delhi | F45: Aarav Mehta | G45: Furniture | H45: Bookshelf | I45: 2 | J45: 5499 | K45: 0.2 | L45: UPI | M45: Delivered | N45: =Table1[[#This Row],[Quantity]]*Table1[[#This Row],[Unit Price (₹)]]*(1-Table1[[#This Row],[Discount %]]) -> 8798.4 | O45: =TEXT(Table1[[#This Row],[Order Date]],"mmmm") -> March | P45: =IF(Table1[[#This Row],[Revenue (₹) ← add]]>=15000,"High Value",IF(Table1[[#This Row],[Revenue (₹) ← add]]>=5000,"Medium","Low")) -> Medium | Q45: =VLOOKUP(Table1[[#This Row],[Product]],Table2[],4,FALSE) -> 3300 | R45: =Table1[[#This Row],[Revenue (₹) ← add]]-Table1[[#This Row],[Cost Price ← add]] -> 5498.4 | S45: =IF(C45="", "",Table1[[#This Row],[Delivery Date]]-Table1[[#This Row],[Order Date]]) -> 6 | T45: =TEXT(Table1[[#This Row],[Order Date]],"DDDD") -> Tuesday
A46: ORD1045 | B46: 45727 | C46: 45730 | D46: West | E46: Ahmedabad | F46: Vikram Shah | G46: Electronics | H46: Bluetooth Speaker | I46: 4 | J46: 2499 | K46: 0 | L46: UPI | M46: Delivered | N46: =Table1[[#This Row],[Quantity]]*Table1[[#This Row],[Unit Price (₹)]]*(1-Table1[[#This Row],[Discount %]]) -> 9996 | O46: =TEXT(Table1[[#This Row],[Order Date]],"mmmm") -> March | P46: =IF(Table1[[#This Row],[Revenue (₹) ← add]]>=15000,"High Value",IF(Table1[[#This Row],[Revenue (₹) ← add]]>=5000,"Medium","Low")) -> Medium | Q46: =VLOOKUP(Table1[[#This Row],[Product]],Table2[],4,FALSE) -> 1500 | R46: =Table1[[#This Row],[Revenue (₹) ← add]]-Table1[[#This Row],[Cost Price ← add]] -> 8496 | S46: =IF(C46="", "",Table1[[#This Row],[Delivery Date]]-Table1[[#This Row],[Order Date]]) -> 3 | T46: =TEXT(Table1[[#This Row],[Order Date]],"DDDD") -> Tuesday
A47: ORD1046 | B47: 45729 | C47: 45732 | D47: East | E47: Kolkata | F47: Rohit Das | G47: Stationery | H47: Desk Organizer | I47: 9 | J47: 599 | K47: 0.1 | L47: COD | M47: Delivered | N47: =Table1[[#This Row],[Quantity]]*Table1[[#This Row],[Unit Price (₹)]]*(1-Table1[[#This Row],[Discount %]]) -> 4851.9 | O47: =TEXT(Table1[[#This Row],[Order Date]],"mmmm") -> March | P47: =IF(Table1[[#This Row],[Revenue (₹) ← add]]>=15000,"High Value",IF(Table1[[#This Row],[Revenue (₹) ← add]]>=5000,"Medium","Low")) -> Low | Q47: =VLOOKUP(Table1[[#This Row],[Product]],Table2[],4,FALSE) -> 320 | R47: =Table1[[#This Row],[Revenue (₹) ← add]]-Table1[[#This Row],[Cost Price ← add]] -> 4531.9 | S47: =IF(C47="", "",Table1[[#This Row],[Delivery Date]]-Table1[[#This Row],[Order Date]]) -> 3 | T47: =TEXT(Table1[[#This Row],[Order Date]],"DDDD") -> Thursday
A48: ORD1047 | B48: 45734 | C48: 45743 | D48: West | E48: Mumbai | F48: Vikram Shah | G48: Electronics | H48: Headphones | I48: 3 | J48: 1999 | K48: 0.2 | L48: UPI | M48: Returned | N48: =Table1[[#This Row],[Quantity]]*Table1[[#This Row],[Unit Price (₹)]]*(1-Table1[[#This Row],[Discount %]]) -> 4797.6 | O48: =TEXT(Table1[[#This Row],[Order Date]],"mmmm") -> March | P48: =IF(Table1[[#This Row],[Revenue (₹) ← add]]>=15000,"High Value",IF(Table1[[#This Row],[Revenue (₹) ← add]]>=5000,"Medium","Low")) -> Low | Q48: =VLOOKUP(Table1[[#This Row],[Product]],Table2[],4,FALSE) -> 1100 | R48: =Table1[[#This Row],[Revenue (₹) ← add]]-Table1[[#This Row],[Cost Price ← add]] -> 3697.6 | S48: =IF(C48="", "",Table1[[#This Row],[Delivery Date]]-Table1[[#This Row],[Order Date]]) -> 9 | T48: =TEXT(Table1[[#This Row],[Order Date]],"DDDD") -> Tuesday
A49: ORD1048 | B49: 45742 | C49: 45748 | D49: East | E49: Kolkata | F49: Ananya Sen | G49: Furniture | H49: Bookshelf | I49: 3 | J49: 5499 | K49: 0.2 | L49: UPI | M49: Delivered | N49: =Table1[[#This Row],[Quantity]]*Table1[[#This Row],[Unit Price (₹)]]*(1-Table1[[#This Row],[Discount %]]) -> 13197.6 | O49: =TEXT(Table1[[#This Row],[Order Date]],"mmmm") -> March | P49: =IF(Table1[[#This Row],[Revenue (₹) ← add]]>=15000,"High Value",IF(Table1[[#This Row],[Revenue (₹) ← add]]>=5000,"Medium","Low")) -> Medium | Q49: =VLOOKUP(Table1[[#This Row],[Product]],Table2[],4,FALSE) -> 3300 | R49: =Table1[[#This Row],[Revenue (₹) ← add]]-Table1[[#This Row],[Cost Price ← add]] -> 9897.6 | S49: =IF(C49="", "",Table1[[#This Row],[Delivery Date]]-Table1[[#This Row],[Order Date]]) -> 6 | T49: =TEXT(Table1[[#This Row],[Order Date]],"DDDD") -> Wednesday
A50: ORD1049 | B50: 45745 | D50: West | E50: Mumbai | F50: Vikram Shah | G50: Electronics | H50: Bluetooth Speaker | I50: 6 | J50: 2499 | K50: 0.1 | L50: Credit Card | M50: Cancelled | N50: =Table1[[#This Row],[Quantity]]*Table1[[#This Row],[Unit Price (₹)]]*(1-Table1[[#This Row],[Discount %]]) -> 13494.6 | O50: =TEXT(Table1[[#This Row],[Order Date]],"mmmm") -> March | P50: =IF(Table1[[#This Row],[Revenue (₹) ← add]]>=15000,"High Value",IF(Table1[[#This Row],[Revenue (₹) ← add]]>=5000,"Medium","Low")) -> Medium | Q50: =VLOOKUP(Table1[[#This Row],[Product]],Table2[],4,FALSE) -> 1500 | R50: =Table1[[#This Row],[Revenue (₹) ← add]]-Table1[[#This Row],[Cost Price ← add]] -> 11994.6 | S50: =IF(C50="", "",Table1[[#This Row],[Delivery Date]]-Table1[[#This Row],[Order Date]]) | T50: =TEXT(Table1[[#This Row],[Order Date]],"DDDD") -> Saturday
A51: ORD1050 | B51: 45746 | C51: 45753 | D51: East | E51: Kolkata | F51: Rohit Das | G51: Clothing | H51: Denim Jacket | I51: 4 | J51: 2999 | K51: 0.1 | L51: UPI | M51: Delivered | N51: =Table1[[#This Row],[Quantity]]*Table1[[#This Row],[Unit Price (₹)]]*(1-Table1[[#This Row],[Discount %]]) -> 10796.4 | O51: =TEXT(Table1[[#This Row],[Order Date]],"mmmm") -> March | P51: =IF(Table1[[#This Row],[Revenue (₹) ← add]]>=15000,"High Value",IF(Table1[[#This Row],[Revenue (₹) ← add]]>=5000,"Medium","Low")) -> Medium | Q51: =VLOOKUP(Table1[[#This Row],[Product]],Table2[],4,FALSE) -> 1700 | R51: =Table1[[#This Row],[Revenue (₹) ← add]]-Table1[[#This Row],[Cost Price ← add]] -> 9096.4 | S51: =IF(C51="", "",Table1[[#This Row],[Delivery Date]]-Table1[[#This Row],[Order Date]]) -> 7 | T51: =TEXT(Table1[[#This Row],[Order Date]],"DDDD") -> Sunday
A52: ORD1051 | B52: 45747 | C52: 45753 | D52: West | E52: Pune | F52: Vikram Shah | G52: Electronics | H52: Power Bank | I52: 2 | J52: 1499 | K52: 0 | L52: Debit Card | M52: Delivered | N52: =Table1[[#This Row],[Quantity]]*Table1[[#This Row],[Unit Price (₹)]]*(1-Table1[[#This Row],[Discount %]]) -> 2998 | O52: =TEXT(Table1[[#This Row],[Order Date]],"mmmm") -> March | P52: =IF(Table1[[#This Row],[Revenue (₹) ← add]]>=15000,"High Value",IF(Table1[[#This Row],[Revenue (₹) ← add]]>=5000,"Medium","Low")) -> Low | Q52: =VLOOKUP(Table1[[#This Row],[Product]],Table2[],4,FALSE) -> 850 | R52: =Table1[[#This Row],[Revenue (₹) ← add]]-Table1[[#This Row],[Cost Price ← add]] -> 2148 | S52: =IF(C52="", "",Table1[[#This Row],[Delivery Date]]-Table1[[#This Row],[Order Date]]) -> 6 | T52: =TEXT(Table1[[#This Row],[Order Date]],"DDDD") -> Monday
A53: ORD1052 | B53: 45749 | C53: 45753 | D53: North | E53: Lucknow | F53: Aarav Mehta | G53: Stationery | H53: Gel Pen Box | I53: 12 | J53: 249 | K53: 0.1 | L53: Debit Card | M53: Delivered | N53: =Table1[[#This Row],[Quantity]]*Table1[[#This Row],[Unit Price (₹)]]*(1-Table1[[#This Row],[Discount %]]) -> 2689.2 | O53: =TEXT(Table1[[#This Row],[Order Date]],"mmmm") -> April | P53: =IF(Table1[[#This Row],[Revenue (₹) ← add]]>=15000,"High Value",IF(Table1[[#This Row],[Revenue (₹) ← add]]>=5000,"Medium","Low")) -> Low | Q53: =VLOOKUP(Table1[[#This Row],[Product]],Table2[],4,FALSE) -> 120 | R53: =Table1[[#This Row],[Revenue (₹) ← add]]-Table1[[#This Row],[Cost Price ← add]] -> 2569.2 | S53: =IF(C53="", "",Table1[[#This Row],[Delivery Date]]-Table1[[#This Row],[Order Date]]) -> 4 | T53: =TEXT(Table1[[#This Row],[Order Date]],"DDDD") -> Wednesday
A54: ORD1053 | B54: 45754 | D54: South | E54: Hyderabad | F54: Karthik Iyer | G54: Electronics | H54: Bluetooth Speaker | I54: 6 | J54: 2499 | K54: 0.2 | L54: COD | M54: Cancelled | N54: =Table1[[#This Row],[Quantity]]*Table1[[#This Row],[Unit Price (₹)]]*(1-Table1[[#This Row],[Discount %]]) -> 11995.2 | O54: =TEXT(Table1[[#This Row],[Order Date]],"mmmm") -> April | P54: =IF(Table1[[#This Row],[Revenue (₹) ← add]]>=15000,"High Value",IF(Table1[[#This Row],[Revenue (₹) ← add]]>=5000,"Medium","Low")) -> Medium | Q54: =VLOOKUP(Table1[[#This Row],[Product]],Table2[],4,FALSE) -> 1500 | R54: =Table1[[#This Row],[Revenue (₹) ← add]]-Table1[[#This Row],[Cost Price ← add]] -> 10495.2 | S54: =IF(C54="", "",Table1[[#This Row],[Delivery Date]]-Table1[[#This Row],[Order Date]]) | T54: =TEXT(Table1[[#This Row],[Order Date]],"DDDD") -> Monday
A55: ORD1054 | B55: 45754 | C55: 45756 | D55: West | E55: Mumbai | F55: Neha Joshi | G55: Stationery | H55: Gel Pen Box | I55: 16 | J55: 249 | K55: 0 | L55: Net Banking | M55: Delivered | N55: =Table1[[#This Row],[Quantity]]*Table1[[#This Row],[Unit Price (₹)]]*(1-Table1[[#This Row],[Discount %]]) -> 3984 | O55: =TEXT(Table1[[#This Row],[Order Date]],"mmmm") -> April | P55: =IF(Table1[[#This Row],[Revenue (₹) ← add]]>=15000,"High Value",IF(Table1[[#This Row],[Revenue (₹) ← add]]>=5000,"Medium","Low")) -> Low | Q55: =VLOOKUP(Table1[[#This Row],[Product]],Table2[],4,FALSE) -> 120 | R55: =Table1[[#This Row],[Revenue (₹) ← add]]-Table1[[#This Row],[Cost Price ← add]] -> 3864 | S55: =IF(C55="", "",Table1[[#This Row],[Delivery Date]]-Table1[[#This Row],[Order Date]]) -> 2 | T55: =TEXT(Table1[[#This Row],[Order Date]],"DDDD") -> Monday
A56: ORD1055 | B56: 45754 | C56: 45758 | D56: South | E56: Chennai | F56: Karthik Iyer | G56: Stationery | H56: Notebook Pack | I56: 6 | J56: 349 | K56: 0.15 | L56: Net Banking | M56: Delivered | N56: =Table1[[#This Row],[Quantity]]*Table1[[#This Row],[Unit Price (₹)]]*(1-Table1[[#This Row],[Discount %]]) -> 1779.9 | O56: =TEXT(Table1[[#This Row],[Order Date]],"mmmm") -> April | P56: =IF(Table1[[#This Row],[Revenue (₹) ← add]]>=15000,"High Value",IF(Table1[[#This Row],[Revenue (₹) ← add]]>=5000,"Medium","Low")) -> Low | Q56: =VLOOKUP(Table1[[#This Row],[Product]],Table2[],4,FALSE) -> 180 | R56: =Table1[[#This Row],[Revenue (₹) ← add]]-Table1[[#This Row],[Cost Price ← add]] -> 1599.9 | S56: =IF(C56="", "",Table1[[#This Row],[Delivery Date]]-Table1[[#This Row],[Order Date]]) -> 4 | T56: =TEXT(Table1[[#This Row],[Order Date]],"DDDD") -> Monday
A57: ORD1056 | B57: 45756 | C57: 45760 | D57: North | E57: Lucknow | F57: Simran Kaur | G57: Electronics | H57: Power Bank | I57: 5 | J57: 1499 | K57: 0.05 | L57: COD | M57: Delivered | N57: =Table1[[#This Row],[Quantity]]*Table1[[#This Row],[Unit Price (₹)]]*(1-Table1[[#This Row],[Discount %]]) -> 7120.25 | O57: =TEXT(Table1[[#This Row],[Order Date]],"mmmm") -> April | P57: =IF(Table1[[#This Row],[Revenue (₹) ← add]]>=15000,"High Value",IF(Table1[[#This Row],[Revenue (₹) ← add]]>=5000,"Medium","Low")) -> Medium | Q57: =VLOOKUP(Table1[[#This Row],[Product]],Table2[],4,FALSE) -> 850 | R57: =Table1[[#This Row],[Revenue (₹) ← add]]-Table1[[#This Row],[Cost Price ← add]] -> 6270.25 | S57: =IF(C57="", "",Table1[[#This Row],[Delivery Date]]-Table1[[#This Row],[Order Date]]) -> 4 | T57: =TEXT(Table1[[#This Row],[Order Date]],"DDDD") -> Wednesday
A58: ORD1057 | B58: 45757 | C58: 45759 | D58: North | E58: Lucknow | F58: Aarav Mehta | G58: Stationery | H58: Desk Organizer | I58: 11 | J58: 599 | K58: 0.05 | L58: Debit Card | M58: Delivered | N58: =Table1[[#This Row],[Quantity]]*Table1[[#This Row],[Unit Price (₹)]]*(1-Table1[[#This Row],[Discount %]]) -> 6259.55 | O58: =TEXT(Table1[[#This Row],[Order Date]],"mmmm") -> April | P58: =IF(Table1[[#This Row],[Revenue (₹) ← add]]>=15000,"High Value",IF(Table1[[#This Row],[Revenue (₹) ← add]]>=5000,"Medium","Low")) -> Medium | Q58: =VLOOKUP(Table1[[#This Row],[Product]],Table2[],4,FALSE) -> 320 | R58: =Table1[[#This Row],[Revenue (₹) ← add]]-Table1[[#This Row],[Cost Price ← add]] -> 5939.55 | S58: =IF(C58="", "",Table1[[#This Row],[Delivery Date]]-Table1[[#This Row],[Order Date]]) -> 2 | T58: =TEXT(Table1[[#This Row],[Order Date]],"DDDD") -> Thursday
A59: ORD1058 | B59: 45757 | C59: 45763 | D59: South | E59: Chennai | F59: Meera Nair | G59: Electronics | H59: Power Bank | I59: 2 | J59: 1499 | K59: 0.2 | L59: Net Banking | M59: Delivered | N59: =Table1[[#This Row],[Quantity]]*Table1[[#This Row],[Unit Price (₹)]]*(1-Table1[[#This Row],[Discount %]]) -> 2398.4 | O59: =TEXT(Table1[[#This Row],[Order Date]],"mmmm") -> April | P59: =IF(Table1[[#This Row],[Revenue (₹) ← add]]>=15000,"High Value",IF(Table1[[#This Row],[Revenue (₹) ← add]]>=5000,"Medium","Low")) -> Low | Q59: =VLOOKUP(Table1[[#This Row],[Product]],Table2[],4,FALSE) -> 850 | R59: =Table1[[#This Row],[Revenue (₹) ← add]]-Table1[[#This Row],[Cost Price ← add]] -> 1548.4 | S59: =IF(C59="", "",Table1[[#This Row],[Delivery Date]]-Table1[[#This Row],[Order Date]]) -> 6 | T59: =TEXT(Table1[[#This Row],[Order Date]],"DDDD") -> Thursday
A60: ORD1059 | B60: 45761 | D60: West | E60: Pune | F60: Vikram Shah | G60: Electronics | H60: Bluetooth Speaker | I60: 4 | J60: 2499 | K60: 0 | L60: UPI | M60: Cancelled | N60: =Table1[[#This Row],[Quantity]]*Table1[[#This Row],[Unit Price (₹)]]*(1-Table1[[#This Row],[Discount %]]) -> 9996 | O60: =TEXT(Table1[[#This Row],[Order Date]],"mmmm") -> April | P60: =IF(Table1[[#This Row],[Revenue (₹) ← add]]>=15000,"High Value",IF(Table1[[#This Row],[Revenue (₹) ← add]]>=5000,"Medium","Low")) -> Medium | Q60: =VLOOKUP(Table1[[#This Row],[Product]],Table2[],4,FALSE) -> 1500 | R60: =Table1[[#This Row],[Revenue (₹) ← add]]-Table1[[#This Row],[Cost Price ← add]] -> 8496 | S60: =IF(C60="", "",Table1[[#This Row],[Delivery Date]]-Table1[[#This Row],[Order Date]]) | T60: =TEXT(Table1[[#This Row],[Order Date]],"DDDD") -> Monday
A61: ORD1060 | B61: 45762 | D61: East | E61: Kolkata | F61: Ananya Sen | G61: Furniture | H61: Study Desk | I61: 2 | J61: 8499 | K61: 0.15 | L61: UPI | M61: Cancelled | N61: =Table1[[#This Row],[Quantity]]*Table1[[#This Row],[Unit Price (₹)]]*(1-Table1[[#This Row],[Discount %]]) -> 14448.3 | O61: =TEXT(Table1[[#This Row],[Order Date]],"mmmm") -> April | P61: =IF(Table1[[#This Row],[Revenue (₹) ← add]]>=15000,"High Value",IF(Table1[[#This Row],[Revenue (₹) ← add]]>=5000,"Medium","Low")) -> Medium | Q61: =VLOOKUP(Table1[[#This Row],[Product]],Table2[],4,FALSE) -> 5200 | R61: =Table1[[#This Row],[Revenue (₹) ← add]]-Table1[[#This Row],[Cost Price ← add]] -> 9248.3 | S61: =IF(C61="", "",Table1[[#This Row],[Delivery Date]]-Table1[[#This Row],[Order Date]]) | T61: =TEXT(Table1[[#This Row],[Order Date]],"DDDD") -> Tuesday
A62: ORD1061 | B62: 45765 | C62: 45768 | D62: West | E62: Mumbai | F62: Vikram Shah | G62: Furniture | H62: Bookshelf | I62: 2 | J62: 5499 | K62: 0.05 | L62: Net Banking | M62: Delivered | N62: =Table1[[#This Row],[Quantity]]*Table1[[#This Row],[Unit Price (₹)]]*(1-Table1[[#This Row],[Discount %]]) -> 10448.1 | O62: =TEXT(Table1[[#This Row],[Order Date]],"mmmm") -> April | P62: =IF(Table1[[#This Row],[Revenue (₹) ← add]]>=15000,"High Value",IF(Table1[[#This Row],[Revenue (₹) ← add]]>=5000,"Medium","Low")) -> Medium | Q62: =VLOOKUP(Table1[[#This Row],[Product]],Table2[],4,FALSE) -> 3300 | R62: =Table1[[#This Row],[Revenue (₹) ← add]]-Table1[[#This Row],[Cost Price ← add]] -> 7148.1 | S62: =IF(C62="", "",Table1[[#This Row],[Delivery Date]]-Table1[[#This Row],[Order Date]]) -> 3 | T62: =TEXT(Table1[[#This Row],[Order Date]],"DDDD") -> Friday
A63: ORD1062 | B63: 45766 | C63: 45768 | D63: North | E63: Chandigarh | F63: Simran Kaur | G63: Stationery | H63: Gel Pen Box | I63: 23 | J63: 249 | K63: 0 | L63: UPI | M63: Returned | N63: =Table1[[#This Row],[Quantity]]*Table1[[#This Row],[Unit Price (₹)]]*(1-Table1[[#This Row],[Discount %]]) -> 5727 | O63: =TEXT(Table1[[#This Row],[Order Date]],"mmmm") -> April | P63: =IF(Table1[[#This Row],[Revenue (₹) ← add]]>=15000,"High Value",IF(Table1[[#This Row],[Revenue (₹) ← add]]>=5000,"Medium","Low")) -> Medium | Q63: =VLOOKUP(Table1[[#This Row],[Product]],Table2[],4,FALSE) -> 120 | R63: =Table1[[#This Row],[Revenue (₹) ← add]]-Table1[[#This Row],[Cost Price ← add]] -> 5607 | S63: =IF(C63="", "",Table1[[#This Row],[Delivery Date]]-Table1[[#This Row],[Order Date]]) -> 2 | T63: =TEXT(Table1[[#This Row],[Order Date]],"DDDD") -> Saturday
A64: ORD1063 | B64: 45767 | C64: 45769 | D64: South | E64: Hyderabad | F64: Meera Nair | G64: Electronics | H64: Power Bank | I64: 6 | J64: 1499 | K64: 0.1 | L64: Credit Card | M64: Delivered | N64: =Table1[[#This Row],[Quantity]]*Table1[[#This Row],[Unit Price (₹)]]*(1-Table1[[#This Row],[Discount %]]) -> 8094.6 | O64: =TEXT(Table1[[#This Row],[Order Date]],"mmmm") -> April | P64: =IF(Table1[[#This Row],[Revenue (₹) ← add]]>=15000,"High Value",IF(Table1[[#This Row],[Revenue (₹) ← add]]>=5000,"Medium","Low")) -> Medium | Q64: =VLOOKUP(Table1[[#This Row],[Product]],Table2[],4,FALSE) -> 850 | R64: =Table1[[#This Row],[Revenue (₹) ← add]]-Table1[[#This Row],[Cost Price ← add]] -> 7244.6 | S64: =IF(C64="", "",Table1[[#This Row],[Delivery Date]]-Table1[[#This Row],[Order Date]]) -> 2 | T64: =TEXT(Table1[[#This Row],[Order Date]],"DDDD") -> Sunday
A65: ORD1064 | B65: 45768 | C65: 45772 | D65: North | E65: Chandigarh | F65: Simran Kaur | G65: Electronics | H65: Power Bank | I65: 3 | J65: 1499 | K65: 0.1 | L65: UPI | M65: Delivered | N65: =Table1[[#This Row],[Quantity]]*Table1[[#This Row],[Unit Price (₹)]]*(1-Table1[[#This Row],[Discount %]]) -> 4047.3 | O65: =TEXT(Table1[[#This Row],[Order Date]],"mmmm") -> April | P65: =IF(Table1[[#This Row],[Revenue (₹) ← add]]>=15000,"High Value",IF(Table1[[#This Row],[Revenue (₹) ← add]]>=5000,"Medium","Low")) -> Low | Q65: =VLOOKUP(Table1[[#This Row],[Product]],Table2[],4,FALSE) -> 850 | R65: =Table1[[#This Row],[Revenue (₹) ← add]]-Table1[[#This Row],[Cost Price ← add]] -> 3197.3 | S65: =IF(C65="", "",Table1[[#This Row],[Delivery Date]]-Table1[[#This Row],[Order Date]]) -> 4 | T65: =TEXT(Table1[[#This Row],[Order Date]],"DDDD") -> Monday
A66: ORD1065 | B66: 45768 | C66: 45777 | D66: North | E66: Delhi | F66: Simran Kaur | G66: Furniture | H66: Study Desk | I66: 3 | J66: 8499 | K66: 0.05 | L66: Net Banking | M66: Delivered | N66: =Table1[[#This Row],[Quantity]]*Table1[[#This Row],[Unit Price (₹)]]*(1-Table1[[#This Row],[Discount %]]) -> 24222.15 | O66: =TEXT(Table1[[#This Row],[Order Date]],"mmmm") -> April | P66: =IF(Table1[[#This Row],[Revenue (₹) ← add]]>=15000,"High Value",IF(Table1[[#This Row],[Revenue (₹) ← add]]>=5000,"Medium","Low")) -> High Value | Q66: =VLOOKUP(Table1[[#This Row],[Product]],Table2[],4,FALSE) -> 5200 | R66: =Table1[[#This Row],[Revenue (₹) ← add]]-Table1[[#This Row],[Cost Price ← add]] -> 19022.15 | S66: =IF(C66="", "",Table1[[#This Row],[Delivery Date]]-Table1[[#This Row],[Order Date]]) -> 9 | T66: =TEXT(Table1[[#This Row],[Order Date]],"DDDD") -> Monday
A67: ORD1066 | B67: 45772 | C67: 45781 | D67: South | E67: Chennai | F67: Meera Nair | G67: Stationery | H67: Gel Pen Box | I67: 9 | J67: 249 | K67: 0.15 | L67: UPI | M67: Returned | N67: =Table1[[#This Row],[Quantity]]*Table1[[#This Row],[Unit Price (₹)]]*(1-Table1[[#This Row],[Discount %]]) -> 1904.85 | O67: =TEXT(Table1[[#This Row],[Order Date]],"mmmm") -> April | P67: =IF(Table1[[#This Row],[Revenue (₹) ← add]]>=15000,"High Value",IF(Table1[[#This Row],[Revenue (₹) ← add]]>=5000,"Medium","Low")) -> Low | Q67: =VLOOKUP(Table1[[#This Row],[Product]],Table2[],4,FALSE) -> 120 | R67: =Table1[[#This Row],[Revenue (₹) ← add]]-Table1[[#This Row],[Cost Price ← add]] -> 1784.85 | S67: =IF(C67="", "",Table1[[#This Row],[Delivery Date]]-Table1[[#This Row],[Order Date]]) -> 9 | T67: =TEXT(Table1[[#This Row],[Order Date]],"DDDD") -> Friday
A68: ORD1067 | B68: 45772 | C68: 45780 | D68: North | E68: Delhi | F68: Simran Kaur | G68: Electronics | H68: Headphones | I68: 3 | J68: 1999 | K68: 0.1 | L68: COD | M68: Delivered | N68: =Table1[[#This Row],[Quantity]]*Table1[[#This Row],[Unit Price (₹)]]*(1-Table1[[#This Row],[Discount %]]) -> 5397.3 | O68: =TEXT(Table1[[#This Row],[Order Date]],"mmmm") -> April | P68: =IF(Table1[[#This Row],[Revenue (₹) ← add]]>=15000,"High Value",IF(Table1[[#This Row],[Revenue (₹) ← add]]>=5000,"Medium","Low")) -> Medium | Q68: =VLOOKUP(Table1[[#This Row],[Product]],Table2[],4,FALSE) -> 1100 | R68: =Table1[[#This Row],[Revenue (₹) ← add]]-Table1[[#This Row],[Cost Price ← add]] -> 4297.3 | S68: =IF(C68="", "",Table1[[#This Row],[Delivery Date]]-Table1[[#This Row],[Order Date]]) -> 8 | T68: =TEXT(Table1[[#This Row],[Order Date]],"DDDD") -> Friday
A69: ORD1068 | B69: 45776 | C69: 45780 | D69: North | E69: Chandigarh | F69: Aarav Mehta | G69: Clothing | H69: Cotton T-Shirt | I69: 6 | J69: 599 | K69: 0.05 | L69: Debit Card | M69: Delivered | N69: =Table1[[#This Row],[Quantity]]*Table1[[#This Row],[Unit Price (₹)]]*(1-Table1[[#This Row],[Discount %]]) -> 3414.3 | O69: =TEXT(Table1[[#This Row],[Order Date]],"mmmm") -> April | P69: =IF(Table1[[#This Row],[Revenue (₹) ← add]]>=15000,"High Value",IF(Table1[[#This Row],[Revenue (₹) ← add]]>=5000,"Medium","Low")) -> Low | Q69: =VLOOKUP(Table1[[#This Row],[Product]],Table2[],4,FALSE) -> 300 | R69: =Table1[[#This Row],[Revenue (₹) ← add]]-Table1[[#This Row],[Cost Price ← add]] -> 3114.3 | S69: =IF(C69="", "",Table1[[#This Row],[Delivery Date]]-Table1[[#This Row],[Order Date]]) -> 4 | T69: =TEXT(Table1[[#This Row],[Order Date]],"DDDD") -> Tuesday
A70: ORD1069 | B70: 45777 | C70: 45781 | D70: North | E70: Chandigarh | F70: Aarav Mehta | G70: Electronics | H70: Headphones | I70: 4 | J70: 1999 | K70: 0.15 | L70: Credit Card | M70: Delivered | N70: =Table1[[#This Row],[Quantity]]*Table1[[#This Row],[Unit Price (₹)]]*(1-Table1[[#This Row],[Discount %]]) -> 6796.6 | O70: =TEXT(Table1[[#This Row],[Order Date]],"mmmm") -> April | P70: =IF(Table1[[#This Row],[Revenue (₹) ← add]]>=15000,"High Value",IF(Table1[[#This Row],[Revenue (₹) ← add]]>=5000,"Medium","Low")) -> Medium | Q70: =VLOOKUP(Table1[[#This Row],[Product]],Table2[],4,FALSE) -> 1100 | R70: =Table1[[#This Row],[Revenue (₹) ← add]]-Table1[[#This Row],[Cost Price ← add]] -> 5696.6 | S70: =IF(C70="", "",Table1[[#This Row],[Delivery Date]]-Table1[[#This Row],[Order Date]]) -> 4 | T70: =TEXT(Table1[[#This Row],[Order Date]],"DDDD") -> Wednesday
A71: ORD1070 | B71: 45779 | C71: 45783 | D71: North | E71: Lucknow | F71: Simran Kaur | G71: Clothing | H71: Denim Jacket | I71: 2 | J71: 2999 | K71: 0 | L71: Debit Card | M71: Delivered | N71: =Table1[[#This Row],[Quantity]]*Table1[[#This Row],[Unit Price (₹)]]*(1-Table1[[#This Row],[Discount %]]) -> 5998 | O71: =TEXT(Table1[[#This Row],[Order Date]],"mmmm") -> May | P71: =IF(Table1[[#This Row],[Revenue (₹) ← add]]>=15000,"High Value",IF(Table1[[#This Row],[Revenue (₹) ← add]]>=5000,"Medium","Low")) -> Medium | Q71: =VLOOKUP(Table1[[#This Row],[Product]],Table2[],4,FALSE) -> 1700 | R71: =Table1[[#This Row],[Revenue (₹) ← add]]-Table1[[#This Row],[Cost Price ← add]] -> 4298 | S71: =IF(C71="", "",Table1[[#This Row],[Delivery Date]]-Table1[[#This Row],[Order Date]]) -> 4 | T71: =TEXT(Table1[[#This Row],[Order Date]],"DDDD") -> Friday
A72: ORD1071 | B72: 45779 | C72: 45784 | D72: North | E72: Delhi | F72: Aarav Mehta | G72: Clothing | H72: Denim Jacket | I72: 1 | J72: 2999 | K72: 0.2 | L72: Net Banking | M72: Delivered | N72: =Table1[[#This Row],[Quantity]]*Table1[[#This Row],[Unit Price (₹)]]*(1-Table1[[#This Row],[Discount %]]) -> 2399.2 | O72: =TEXT(Table1[[#This Row],[Order Date]],"mmmm") -> May | P72: =IF(Table1[[#This Row],[Revenue (₹) ← add]]>=15000,"High Value",IF(Table1[[#This Row],[Revenue (₹) ← add]]>=5000,"Medium","Low")) -> Low | Q72: =VLOOKUP(Table1[[#This Row],[Product]],Table2[],4,FALSE) -> 1700 | R72: =Table1[[#This Row],[Revenue (₹) ← add]]-Table1[[#This Row],[Cost Price ← add]] -> 699.2 | S72: =IF(C72="", "",Table1[[#This Row],[Delivery Date]]-Table1[[#This Row],[Order Date]]) -> 5 | T72: =TEXT(Table1[[#This Row],[Order Date]],"DDDD") -> Friday
A73: ORD1072 | B73: 45780 | C73: 45785 | D73: North | E73: Chandigarh | F73: Aarav Mehta | G73: Electronics | H73: Power Bank | I73: 6 | J73: 1499 | K73: 0.05 | L73: UPI | M73: Delivered | N73: =Table1[[#This Row],[Quantity]]*Table1[[#This Row],[Unit Price (₹)]]*(1-Table1[[#This Row],[Discount %]]) -> 8544.3 | O73: =TEXT(Table1[[#This Row],[Order Date]],"mmmm") -> May | P73: =IF(Table1[[#This Row],[Revenue (₹) ← add]]>=15000,"High Value",IF(Table1[[#This Row],[Revenue (₹) ← add]]>=5000,"Medium","Low")) -> Medium | Q73: =VLOOKUP(Table1[[#This Row],[Product]],Table2[],4,FALSE) -> 850 | R73: =Table1[[#This Row],[Revenue (₹) ← add]]-Table1[[#This Row],[Cost Price ← add]] -> 7694.3 | S73: =IF(C73="", "",Table1[[#This Row],[Delivery Date]]-Table1[[#This Row],[Order Date]]) -> 5 | T73: =TEXT(Table1[[#This Row],[Order Date]],"DDDD") -> Saturday
... A83: ORD1082 | B83: 45789 | C83: 45798 | D83: East | E83: Kolkata | F83: Ananya Sen | G83: Stationery | H83: Desk Organizer | I83: 14 | J83: 599 | K83: 0.1 | L83: Debit Card | M83: Delivered | N83: =Table1[[#This Row],[Quantity]]*Table1[[#This Row],[Unit Price (₹)]]*(1-Table1[[#This Row],[Discount %]]) -> 7547.4 | O83: =TEXT(Table1[[#This Row],[Order Date]],"mmmm") -> May | P83: =IF(Table1[[#This Row],[Revenue (₹) ← add]]>=15000,"High Value",IF(Table1[[#This Row],[Revenue (₹) ← add]]>=5000,"Medium","Low")) -> Medium | Q83: =VLOOKUP(Table1[[#This Row],[Product]],Table2[],4,FALSE) -> 320 | R83: =Table1[[#This Row],[Revenue (₹) ← add]]-Table1[[#This Row],[Cost Price ← add]] -> 7227.4 | S83: =IF(C83="", "",Table1[[#This Row],[Delivery Date]]-Table1[[#This Row],[Order Date]]) -> 9 | T83: =TEXT(Table1[[#This Row],[Order Date]],"DDDD") -> Monday
A84: ORD1083 | B84: 45791 | D84: South | E84: Chennai | F84: Meera Nair | G84: Clothing | H84: Cotton T-Shirt | I84: 7 | J84: 599 | K84: 0.05 | L84: Debit Card | M84: Cancelled | N84: =Table1[[#This Row],[Quantity]]*Table1[[#This Row],[Unit Price (₹)]]*(1-Table1[[#This Row],[Discount %]]) -> 3983.35 | O84: =TEXT(Table1[[#This Row],[Order Date]],"mmmm") -> May | P84: =IF(Table1[[#This Row],[Revenue (₹) ← add]]>=15000,"High Value",IF(Table1[[#This Row],[Revenue (₹) ← add]]>=5000,"Medium","Low")) -> Low | Q84: =VLOOKUP(Table1[[#This Row],[Product]],Table2[],4,FALSE) -> 300 | R84: =Table1[[#This Row],[Revenue (₹) ← add]]-Table1[[#This Row],[Cost Price ← add]] -> 3683.35 | S84: =IF(C84="", "",Table1[[#This Row],[Delivery Date]]-Table1[[#This Row],[Order Date]]) | T84: =TEXT(Table1[[#This Row],[Order Date]],"DDDD") -> Wednesday
A85: ORD1084 | B85: 45793 | C85: 45802 | D85: West | E85: Ahmedabad | F85: Neha Joshi | G85: Furniture | H85: Study Desk | I85: 3 | J85: 8499 | K85: 0.15 | L85: Net Banking | M85: Delivered | N85: =Table1[[#This Row],[Quantity]]*Table1[[#This Row],[Unit Price (₹)]]*(1-Table1[[#This Row],[Discount %]]) -> 21672.45 | O85: =TEXT(Table1[[#This Row],[Order Date]],"mmmm") -> May | P85: =IF(Table1[[#This Row],[Revenue (₹) ← add]]>=15000,"High Value",IF(Table1[[#This Row],[Revenue (₹) ← add]]>=5000,"Medium","Low")) -> High Value | Q85: =VLOOKUP(Table1[[#This Row],[Product]],Table2[],4,FALSE) -> 5200 | R85: =Table1[[#This Row],[Revenue (₹) ← add]]-Table1[[#This Row],[Cost Price ← add]] -> 16472.45 | S85: =IF(C85="", "",Table1[[#This Row],[Delivery Date]]-Table1[[#This Row],[Order Date]]) -> 9 | T85: =TEXT(Table1[[#This Row],[Order Date]],"DDDD") -> Friday
A86: ORD1085 | B86: 45794 | C86: 45802 | D86: West | E86: Pune | F86: Neha Joshi | G86: Clothing | H86: Cotton T-Shirt | I86: 5 | J86: 599 | K86: 0.2 | L86: Credit Card | M86: Delivered | N86: =Table1[[#This Row],[Quantity]]*Table1[[#This Row],[Unit Price (₹)]]*(1-Table1[[#This Row],[Discount %]]) -> 2396 | O86: =TEXT(Table1[[#This Row],[Order Date]],"mmmm") -> May | P86: =IF(Table1[[#This Row],[Revenue (₹) ← add]]>=15000,"High Value",IF(Table1[[#This Row],[Revenue (₹) ← add]]>=5000,"Medium","Low")) -> Low | Q86: =VLOOKUP(Table1[[#This Row],[Product]],Table2[],4,FALSE) -> 300 | R86: =Table1[[#This Row],[Revenue (₹) ← add]]-Table1[[#This Row],[Cost Price ← add]] -> 2096 | S86: =IF(C86="", "",Table1[[#This Row],[Delivery Date]]-Table1[[#This Row],[Order Date]]) -> 8 | T86: =TEXT(Table1[[#This Row],[Order Date]],"DDDD") -> Saturday
A87: ORD1086 | B87: 45797 | C87: 45803 | D87: West | E87: Ahmedabad | F87: Vikram Shah | G87: Clothing | H87: Denim Jacket | I87: 4 | J87: 2999 | K87: 0.05 | L87: UPI | M87: Delivered | N87: =Table1[[#This Row],[Quantity]]*Table1[[#This Row],[Unit Price (₹)]]*(1-Table1[[#This Row],[Discount %]]) -> 11396.2 | O87: =TEXT(Table1[[#This Row],[Order Date]],"mmmm") -> May | P87: =IF(Table1[[#This Row],[Revenue (₹) ← add]]>=15000,"High Value",IF(Table1[[#This Row],[Revenue (₹) ← add]]>=5000,"Medium","Low")) -> Medium | Q87: =VLOOKUP(Table1[[#This Row],[Product]],Table2[],4,FALSE) -> 1700 | R87: =Table1[[#This Row],[Revenue (₹) ← add]]-Table1[[#This Row],[Cost Price ← add]] -> 9696.2 | S87: =IF(C87="", "",Table1[[#This Row],[Delivery Date]]-Table1[[#This Row],[Order Date]]) -> 6 | T87: =TEXT(Table1[[#This Row],[Order Date]],"DDDD") -> Tuesday
A88: ORD1087 | B88: 45799 | C88: 45802 | D88: North | E88: Lucknow | F88: Simran Kaur | G88: Stationery | H88: Notebook Pack | I88: 6 | J88: 349 | K88: 0 | L88: Credit Card | M88: Delivered | N88: =Table1[[#This Row],[Quantity]]*Table1[[#This Row],[Unit Price (₹)]]*(1-Table1[[#This Row],[Discount %]]) -> 2094 | O88: =TEXT(Table1[[#This Row],[Order Date]],"mmmm") -> May | P88: =IF(Table1[[#This Row],[Revenue (₹) ← add]]>=15000,"High Value",IF(Table1[[#This Row],[Revenue (₹) ← add]]>=5000,"Medium","Low")) -> Low | Q88: =VLOOKUP(Table1[[#This Row],[Product]],Table2[],4,FALSE) -> 180 | R88: =Table1[[#This Row],[Revenue (₹) ← add]]-Table1[[#This Row],[Cost Price ← add]] -> 1914 | S88: =IF(C88="", "",Table1[[#This Row],[Delivery Date]]-Table1[[#This Row],[Order Date]]) -> 3 | T88: =TEXT(Table1[[#This Row],[Order Date]],"DDDD") -> Thursday
A89: ORD1088 | B89: 45800 | C89: 45809 | D89: East | E89: Bhubaneswar | F89: Rohit Das | G89: Stationery | H89: Desk Organizer | I89: 13 | J89: 599 | K89: 0.05 | L89: Credit Card | M89: Delivered | N89: =Table1[[#This Row],[Quantity]]*Table1[[#This Row],[Unit Price (₹)]]*(1-Table1[[#This Row],[Discount %]]) -> 7397.65 | O89: =TEXT(Table1[[#This Row],[Order Date]],"mmmm") -> May | P89: =IF(Table1[[#This Row],[Revenue (₹) ← add]]>=15000,"High Value",IF(Table1[[#This Row],[Revenue (₹) ← add]]>=5000,"Medium","Low")) -> Medium | Q89: =VLOOKUP(Table1[[#This Row],[Product]],Table2[],4,FALSE) -> 320 | R89: =Table1[[#This Row],[Revenue (₹) ← add]]-Table1[[#This Row],[Cost Price ← add]] -> 7077.65 | S89: =IF(C89="", "",Table1[[#This Row],[Delivery Date]]-Table1[[#This Row],[Order Date]]) -> 9 | T89: =TEXT(Table1[[#This Row],[Order Date]],"DDDD") -> Friday
A90: ORD1089 | B90: 45801 | C90: 45809 | D90: West | E90: Mumbai | F90: Neha Joshi | G90: Stationery | H90: Gel Pen Box | I90: 18 | J90: 249 | K90: 0.05 | L90: UPI | M90: Delivered | N90: =Table1[[#This Row],[Quantity]]*Table1[[#This Row],[Unit Price (₹)]]*(1-Table1[[#This Row],[Discount %]]) -> 4257.9 | O90: =TEXT(Table1[[#This Row],[Order Date]],"mmmm") -> May | P90: =IF(Table1[[#This Row],[Revenue (₹) ← add]]>=15000,"High Value",IF(Table1[[#This Row],[Revenue (₹) ← add]]>=5000,"Medium","Low")) -> Low | Q90: =VLOOKUP(Table1[[#This Row],[Product]],Table2[],4,FALSE) -> 120 | R90: =Table1[[#This Row],[Revenue (₹) ← add]]-Table1[[#This Row],[Cost Price ← add]] -> 4137.9 | S90: =IF(C90="", "",Table1[[#This Row],[Delivery Date]]-Table1[[#This Row],[Order Date]]) -> 8 | T90: =TEXT(Table1[[#This Row],[Order Date]],"DDDD") -> Saturday
A91: ORD1090 | B91: 45802 | C91: 45804 | D91: West | E91: Pune | F91: Neha Joshi | G91: Electronics | H91: Bluetooth Speaker | I91: 4 | J91: 2499 | K91: 0 | L91: Debit Card | M91: Delivered | N91: =Table1[[#This Row],[Quantity]]*Table1[[#This Row],[Unit Price (₹)]]*(1-Table1[[#This Row],[Discount %]]) -> 9996 | O91: =TEXT(Table1[[#This Row],[Order Date]],"mmmm") -> May | P91: =IF(Table1[[#This Row],[Revenue (₹) ← add]]>=15000,"High Value",IF(Table1[[#This Row],[Revenue (₹) ← add]]>=5000,"Medium","Low")) -> Medium | Q91: =VLOOKUP(Table1[[#This Row],[Product]],Table2[],4,FALSE) -> 1500 | R91: =Table1[[#This Row],[Revenue (₹) ← add]]-Table1[[#This Row],[Cost Price ← add]] -> 8496 | S91: =IF(C91="", "",Table1[[#This Row],[Delivery Date]]-Table1[[#This Row],[Order Date]]) -> 2 | T91: =TEXT(Table1[[#This Row],[Order Date]],"DDDD") -> Sunday
A92: ORD1091 | B92: 45802 | C92: 45810 | D92: West | E92: Pune | F92: Neha Joshi | G92: Clothing | H92: Denim Jacket | I92: 4 | J92: 2999 | K92: 0.1 | L92: Net Banking | M92: Delivered | N92: =Table1[[#This Row],[Quantity]]*Table1[[#This Row],[Unit Price (₹)]]*(1-Table1[[#This Row],[Discount %]]) -> 10796.4 | O92: =TEXT(Table1[[#This Row],[Order Date]],"mmmm") -> May | P92: =IF(Table1[[#This Row],[Revenue (₹) ← add]]>=15000,"High Value",IF(Table1[[#This Row],[Revenue (₹) ← add]]>=5000,"Medium","Low")) -> Medium | Q92: =VLOOKUP(Table1[[#This Row],[Product]],Table2[],4,FALSE) -> 1700 | R92: =Table1[[#This Row],[Revenue (₹) ← add]]-Table1[[#This Row],[Cost Price ← add]] -> 9096.4 | S92: =IF(C92="", "",Table1[[#This Row],[Delivery Date]]-Table1[[#This Row],[Order Date]]) -> 8 | T92: =TEXT(Table1[[#This Row],[Order Date]],"DDDD") -> Sunday
A93: ORD1092 | B93: 45804 | C93: 45810 | D93: North | E93: Chandigarh | F93: Simran Kaur | G93: Stationery | H93: Desk Organizer | I93: 8 | J93: 599 | K93: 0 | L93: COD | M93: Delivered | N93: =Table1[[#This Row],[Quantity]]*Table1[[#This Row],[Unit Price (₹)]]*(1-Table1[[#This Row],[Discount %]]) -> 4792 | O93: =TEXT(Table1[[#This Row],[Order Date]],"mmmm") -> May | P93: =IF(Table1[[#This Row],[Revenue (₹) ← add]]>=15000,"High Value",IF(Table1[[#This Row],[Revenue (₹) ← add]]>=5000,"Medium","Low")) -> Low | Q93: =VLOOKUP(Table1[[#This Row],[Product]],Table2[],4,FALSE) -> 320 | R93: =Table1[[#This Row],[Revenue (₹) ← add]]-Table1[[#This Row],[Cost Price ← add]] -> 4472 | S93: =IF(C93="", "",Table1[[#This Row],[Delivery Date]]-Table1[[#This Row],[Order Date]]) -> 6 | T93: =TEXT(Table1[[#This Row],[Order Date]],"DDDD") -> Tuesday
A94: ORD1093 | B94: 45807 | C94: 45810 | D94: North | E94: Chandigarh | F94: Aarav Mehta | G94: Stationery | H94: Gel Pen Box | I94: 16 | J94: 249 | K94: 0.15 | L94: UPI | M94: Delivered | N94: =Table1[[#This Row],[Quantity]]*Table1[[#This Row],[Unit Price (₹)]]*(1-Table1[[#This Row],[Discount %]]) -> 3386.4 | O94: =TEXT(Table1[[#This Row],[Order Date]],"mmmm") -> May | P94: =IF(Table1[[#This Row],[Revenue (₹) ← add]]>=15000,"High Value",IF(Table1[[#This Row],[Revenue (₹) ← add]]>=5000,"Medium","Low")) -> Low | Q94: =VLOOKUP(Table1[[#This Row],[Product]],Table2[],4,FALSE) -> 120 | R94: =Table1[[#This Row],[Revenue (₹) ← add]]-Table1[[#This Row],[Cost Price ← add]] -> 3266.4 | S94: =IF(C94="", "",Table1[[#This Row],[Delivery Date]]-Table1[[#This Row],[Order Date]]) -> 3 | T94: =TEXT(Table1[[#This Row],[Order Date]],"DDDD") -> Friday
A95: ORD1094 | B95: 45808 | C95: 45817 | D95: North | E95: Lucknow | F95: Aarav Mehta | G95: Clothing | H95: Denim Jacket | I95: 3 | J95: 2999 | K95: 0.05 | L95: UPI | M95: Delivered | N95: =Table1[[#This Row],[Quantity]]*Table1[[#This Row],[Unit Price (₹)]]*(1-Table1[[#This Row],[Discount %]]) -> 8547.15 | O95: =TEXT(Table1[[#This Row],[Order Date]],"mmmm") -> May | P95: =IF(Table1[[#This Row],[Revenue (₹) ← add]]>=15000,"High Value",IF(Table1[[#This Row],[Revenue (₹) ← add]]>=5000,"Medium","Low")) -> Medium | Q95: =VLOOKUP(Table1[[#This Row],[Product]],Table2[],4,FALSE) -> 1700 | R95: =Table1[[#This Row],[Revenue (₹) ← add]]-Table1[[#This Row],[Cost Price ← add]] -> 6847.15 | S95: =IF(C95="", "",Table1[[#This Row],[Delivery Date]]-Table1[[#This Row],[Order Date]]) -> 9 | T95: =TEXT(Table1[[#This Row],[Order Date]],"DDDD") -> Saturday
A96: ORD1095 | B96: 45810 | C96: 45813 | D96: South | E96: Hyderabad | F96: Meera Nair | G96: Electronics | H96: Wireless Mouse | I96: 2 | J96: 799 | K96: 0 | L96: COD | M96: Delivered | N96: =Table1[[#This Row],[Quantity]]*Table1[[#This Row],[Unit Price (₹)]]*(1-Table1[[#This Row],[Discount %]]) -> 1598 | O96: =TEXT(Table1[[#This Row],[Order Date]],"mmmm") -> June | P96: =IF(Table1[[#This Row],[Revenue (₹) ← add]]>=15000,"High Value",IF(Table1[[#This Row],[Revenue (₹) ← add]]>=5000,"Medium","Low")) -> Low | Q96: =VLOOKUP(Table1[[#This Row],[Product]],Table2[],4,FALSE) -> 450 | R96: =Table1[[#This Row],[Revenue (₹) ← add]]-Table1[[#This Row],[Cost Price ← add]] -> 1148 | S96: =IF(C96="", "",Table1[[#This Row],[Delivery Date]]-Table1[[#This Row],[Order Date]]) -> 3 | T96: =TEXT(Table1[[#This Row],[Order Date]],"DDDD") -> Monday
... A104: ORD1103 | B104: 45820 | C104: 45824 | D104: East | E104: Bhubaneswar | F104: Rohit Das | G104: Clothing | H104: Cotton T-Shirt | I104: 5 | J104: 599 | K104: 0.1 | L104: Debit Card | M104: Delivered | N104: =Table1[[#This Row],[Quantity]]*Table1[[#This Row],[Unit Price (₹)]]*(1-Table1[[#This Row],[Discount %]]) -> 2695.5 | O104: =TEXT(Table1[[#This Row],[Order Date]],"mmmm") -> June | P104: =IF(Table1[[#This Row],[Revenue (₹) ← add]]>=15000,"High Value",IF(Table1[[#This Row],[Revenue (₹) ← add]]>=5000,"Medium","Low")) -> Low | Q104: =VLOOKUP(Table1[[#This Row],[Product]],Table2[],4,FALSE) -> 300 | R104: =Table1[[#This Row],[Revenue (₹) ← add]]-Table1[[#This Row],[Cost Price ← add]] -> 2395.5 | S104: =IF(C104="", "",Table1[[#This Row],[Delivery Date]]-Table1[[#This Row],[Order Date]]) -> 4 | T104: =TEXT(Table1[[#This Row],[Order Date]],"DDDD") -> Thursday
A105: ORD1104 | B105: 45822 | D105: West | E105: Ahmedabad | F105: Neha Joshi | G105: Clothing | H105: Denim Jacket | I105: 2 | J105: 2999 | K105: 0.05 | L105: Debit Card | M105: Cancelled | N105: =Table1[[#This Row],[Quantity]]*Table1[[#This Row],[Unit Price (₹)]]*(1-Table1[[#This Row],[Discount %]]) -> 5698.1 | O105: =TEXT(Table1[[#This Row],[Order Date]],"mmmm") -> June | P105: =IF(Table1[[#This Row],[Revenue (₹) ← add]]>=15000,"High Value",IF(Table1[[#This Row],[Revenue (₹) ← add]]>=5000,"Medium","Low")) -> Medium | Q105: =VLOOKUP(Table1[[#This Row],[Product]],Table2[],4,FALSE) -> 1700 | R105: =Table1[[#This Row],[Revenue (₹) ← add]]-Table1[[#This Row],[Cost Price ← add]] -> 3998.1 | S105: =IF(C105="", "",Table1[[#This Row],[Delivery Date]]-Table1[[#This Row],[Order Date]]) | T105: =TEXT(Table1[[#This Row],[Order Date]],"DDDD") -> Saturday
A106: ORD1105 | B106: 45823 | C106: 45828 | D106: North | E106: Chandigarh | F106: Aarav Mehta | G106: Electronics | H106: Wireless Mouse | I106: 4 | J106: 799 | K106: 0.1 | L106: COD | M106: Delivered | N106: =Table1[[#This Row],[Quantity]]*Table1[[#This Row],[Unit Price (₹)]]*(1-Table1[[#This Row],[Discount %]]) -> 2876.4 | O106: =TEXT(Table1[[#This Row],[Order Date]],"mmmm") -> June | P106: =IF(Table1[[#This Row],[Revenue (₹) ← add]]>=15000,"High Value",IF(Table1[[#This Row],[Revenue (₹) ← add]]>=5000,"Medium","Low")) -> Low | Q106: =VLOOKUP(Table1[[#This Row],[Product]],Table2[],4,FALSE) -> 450 | R106: =Table1[[#This Row],[Revenue (₹) ← add]]-Table1[[#This Row],[Cost Price ← add]] -> 2426.4 | S106: =IF(C106="", "",Table1[[#This Row],[Delivery Date]]-Table1[[#This Row],[Order Date]]) -> 5 | T106: =TEXT(Table1[[#This Row],[Order Date]],"DDDD") -> Sunday
A107: ORD1106 | B107: 45823 | C107: 45832 | D107: South | E107: Bengaluru | F107: Karthik Iyer | G107: Electronics | H107: Wireless Mouse | I107: 2 | J107: 799 | K107: 0.2 | L107: Credit Card | M107: Delivered | N107: =Table1[[#This Row],[Quantity]]*Table1[[#This Row],[Unit Price (₹)]]*(1-Table1[[#This Row],[Discount %]]) -> 1278.4 | O107: =TEXT(Table1[[#This Row],[Order Date]],"mmmm") -> June | P107: =IF(Table1[[#This Row],[Revenue (₹) ← add]]>=15000,"High Value",IF(Table1[[#This Row],[Revenue (₹) ← add]]>=5000,"Medium","Low")) -> Low | Q107: =VLOOKUP(Table1[[#This Row],[Product]],Table2[],4,FALSE) -> 450 | R107: =Table1[[#This Row],[Revenue (₹) ← add]]-Table1[[#This Row],[Cost Price ← add]] -> 828.4 | S107: =IF(C107="", "",Table1[[#This Row],[Delivery Date]]-Table1[[#This Row],[Order Date]]) -> 9 | T107: =TEXT(Table1[[#This Row],[Order Date]],"DDDD") -> Sunday
A108: ORD1107 | B108: 45824 | C108: 45832 | D108: South | E108: Chennai | F108: Meera Nair | G108: Stationery | H108: Desk Organizer | I108: 14 | J108: 599 | K108: 0 | L108: COD | M108: Delivered | N108: =Table1[[#This Row],[Quantity]]*Table1[[#This Row],[Unit Price (₹)]]*(1-Table1[[#This Row],[Discount %]]) -> 8386 | O108: =TEXT(Table1[[#This Row],[Order Date]],"mmmm") -> June | P108: =IF(Table1[[#This Row],[Revenue (₹) ← add]]>=15000,"High Value",IF(Table1[[#This Row],[Revenue (₹) ← add]]>=5000,"Medium","Low")) -> Medium | Q108: =VLOOKUP(Table1[[#This Row],[Product]],Table2[],4,FALSE) -> 320 | R108: =Table1[[#This Row],[Revenue (₹) ← add]]-Table1[[#This Row],[Cost Price ← add]] -> 8066 | S108: =IF(C108="", "",Table1[[#This Row],[Delivery Date]]-Table1[[#This Row],[Order Date]]) -> 8 | T108: =TEXT(Table1[[#This Row],[Order Date]],"DDDD") -> Monday
A109: ORD1108 | B109: 45824 | C109: 45828 | D109: West | E109: Pune | F109: Neha Joshi | G109: Stationery | H109: Notebook Pack | I109: 22 | J109: 349 | K109: 0.05 | L109: Credit Card | M109: Returned | N109: =Table1[[#This Row],[Quantity]]*Table1[[#This Row],[Unit Price (₹)]]*(1-Table1[[#This Row],[Discount %]]) -> 7294.1 | O109: =TEXT(Table1[[#This Row],[Order Date]],"mmmm") -> June | P109: =IF(Table1[[#This Row],[Revenue (₹) ← add]]>=15000,"High Value",IF(Table1[[#This Row],[Revenue (₹) ← add]]>=5000,"Medium","Low")) -> Medium | Q109: =VLOOKUP(Table1[[#This Row],[Product]],Table2[],4,FALSE) -> 180 | R109: =Table1[[#This Row],[Revenue (₹) ← add]]-Table1[[#This Row],[Cost Price ← add]] -> 7114.1 | S109: =IF(C109="", "",Table1[[#This Row],[Delivery Date]]-Table1[[#This Row],[Order Date]]) -> 4 | T109: =TEXT(Table1[[#This Row],[Order Date]],"DDDD") -> Monday
A110: ORD1109 | B110: 45824 | C110: 45832 | D110: East | E110: Kolkata | F110: Rohit Das | G110: Clothing | H110: Cotton T-Shirt | I110: 7 | J110: 599 | K110: 0.2 | L110: UPI | M110: Delivered | N110: =Table1[[#This Row],[Quantity]]*Table1[[#This Row],[Unit Price (₹)]]*(1-Table1[[#This Row],[Discount %]]) -> 3354.4 | O110: =TEXT(Table1[[#This Row],[Order Date]],"mmmm") -> June | P110: =IF(Table1[[#This Row],[Revenue (₹) ← add]]>=15000,"High Value",IF(Table1[[#This Row],[Revenue (₹) ← add]]>=5000,"Medium","Low")) -> Low | Q110: =VLOOKUP(Table1[[#This Row],[Product]],Table2[],4,FALSE) -> 300 | R110: =Table1[[#This Row],[Revenue (₹) ← add]]-Table1[[#This Row],[Cost Price ← add]] -> 3054.4 | S110: =IF(C110="", "",Table1[[#This Row],[Delivery Date]]-Table1[[#This Row],[Order Date]]) -> 8 | T110: =TEXT(Table1[[#This Row],[Order Date]],"DDDD") -> Monday
A111: ORD1110 | B111: 45827 | C111: 45829 | D111: North | E111: Lucknow | F111: Aarav Mehta | G111: Clothing | H111: Denim Jacket | I111: 1 | J111: 2999 | K111: 0.1 | L111: UPI | M111: Delivered | N111: =Table1[[#This Row],[Quantity]]*Table1[[#This Row],[Unit Price (₹)]]*(1-Table1[[#This Row],[Discount %]]) -> 2699.1 | O111: =TEXT(Table1[[#This Row],[Order Date]],"mmmm") -> June | P111: =IF(Table1[[#This Row],[Revenue (₹) ← add]]>=15000,"High Value",IF(Table1[[#This Row],[Revenue (₹) ← add]]>=5000,"Medium","Low")) -> Low | Q111: =VLOOKUP(Table1[[#This Row],[Product]],Table2[],4,FALSE) -> 1700 | R111: =Table1[[#This Row],[Revenue (₹) ← add]]-Table1[[#This Row],[Cost Price ← add]] -> 999.1 | S111: =IF(C111="", "",Table1[[#This Row],[Delivery Date]]-Table1[[#This Row],[Order Date]]) -> 2 | T111: =TEXT(Table1[[#This Row],[Order Date]],"DDDD") -> Thursday
A112: ORD1111 | B112: 45828 | C112: 45832 | D112: North | E112: Chandigarh | F112: Aarav Mehta | G112: Electronics | H112: Bluetooth Speaker | I112: 4 | J112: 2499 | K112: 0 | L112: UPI | M112: Delivered | N112: =Table1[[#This Row],[Quantity]]*Table1[[#This Row],[Unit Price (₹)]]*(1-Table1[[#This Row],[Discount %]]) -> 9996 | O112: =TEXT(Table1[[#This Row],[Order Date]],"mmmm") -> June | P112: =IF(Table1[[#This Row],[Revenue (₹) ← add]]>=15000,"High Value",IF(Table1[[#This Row],[Revenue (₹) ← add]]>=5000,"Medium","Low")) -> Medium | Q112: =VLOOKUP(Table1[[#This Row],[Product]],Table2[],4,FALSE) -> 1500 | R112: =Table1[[#This Row],[Revenue (₹) ← add]]-Table1[[#This Row],[Cost Price ← add]] -> 8496 | S112: =IF(C112="", "",Table1[[#This Row],[Delivery Date]]-Table1[[#This Row],[Order Date]]) -> 4 | T112: =TEXT(Table1[[#This Row],[Order Date]],"DDDD") -> Friday
A113: ORD1112 | B113: 45830 | C113: 45837 | D113: North | E113: Lucknow | F113: Simran Kaur | G113: Electronics | H113: Wireless Mouse | I113: 3 | J113: 799 | K113: 0.05 | L113: Debit Card | M113: Delivered | N113: =Table1[[#This Row],[Quantity]]*Table1[[#This Row],[Unit Price (₹)]]*(1-Table1[[#This Row],[Discount %]]) -> 2277.15 | O113: =TEXT(Table1[[#This Row],[Order Date]],"mmmm") -> June | P113: =IF(Table1[[#This Row],[Revenue (₹) ← add]]>=15000,"High Value",IF(Table1[[#This Row],[Revenue (₹) ← add]]>=5000,"Medium","Low")) -> Low | Q113: =VLOOKUP(Table1[[#This Row],[Product]],Table2[],4,FALSE) -> 450 | R113: =Table1[[#This Row],[Revenue (₹) ← add]]-Table1[[#This Row],[Cost Price ← add]] -> 1827.15 | S113: =IF(C113="", "",Table1[[#This Row],[Delivery Date]]-Table1[[#This Row],[Order Date]]) -> 7 | T113: =TEXT(Table1[[#This Row],[Order Date]],"DDDD") -> Sunday
A114: ORD1113 | B114: 45831 | C114: 45835 | D114: West | E114: Mumbai | F114: Vikram Shah | G114: Electronics | H114: Power Bank | I114: 6 | J114: 1499 | K114: 0 | L114: UPI | M114: Delivered | N114: =Table1[[#This Row],[Quantity]]*Table1[[#This Row],[Unit Price (₹)]]*(1-Table1[[#This Row],[Discount %]]) -> 8994 | O114: =TEXT(Table1[[#This Row],[Order Date]],"mmmm") -> June | P114: =IF(Table1[[#This Row],[Revenue (₹) ← add]]>=15000,"High Value",IF(Table1[[#This Row],[Revenue (₹) ← add]]>=5000,"Medium","Low")) -> Medium | Q114: =VLOOKUP(Table1[[#This Row],[Product]],Table2[],4,FALSE) -> 850 | R114: =Table1[[#This Row],[Revenue (₹) ← add]]-Table1[[#This Row],[Cost Price ← add]] -> 8144 | S114: =IF(C114="", "",Table1[[#This Row],[Delivery Date]]-Table1[[#This Row],[Order Date]]) -> 4 | T114: =TEXT(Table1[[#This Row],[Order Date]],"DDDD") -> Monday
A115: ORD1114 | B115: 45833 | C115: 45841 | D115: West | E115: Mumbai | F115: Neha Joshi | G115: Clothing | H115: Cotton T-Shirt | I115: 4 | J115: 599 | K115: 0.05 | L115: UPI | M115: Delivered | N115: =Table1[[#This Row],[Quantity]]*Table1[[#This Row],[Unit Price (₹)]]*(1-Table1[[#This Row],[Discount %]]) -> 2276.2 | O115: =TEXT(Table1[[#This Row],[Order Date]],"mmmm") -> June | P115: =IF(Table1[[#This Row],[Revenue (₹) ← add]]>=15000,"High Value",IF(Table1[[#This Row],[Revenue (₹) ← add]]>=5000,"Medium","Low")) -> Low | Q115: =VLOOKUP(Table1[[#This Row],[Product]],Table2[],4,FALSE) -> 300 | R115: =Table1[[#This Row],[Revenue (₹) ← add]]-Table1[[#This Row],[Cost Price ← add]] -> 1976.2 | S115: =IF(C115="", "",Table1[[#This Row],[Delivery Date]]-Table1[[#This Row],[Order Date]]) -> 8 | T115: =TEXT(Table1[[#This Row],[Order Date]],"DDDD") -> Wednesday
A116: ORD1115 | B116: 45840 | C116: 45848 | D116: East | E116: Patna | F116: Ananya Sen | G116: Electronics | H116: Bluetooth Speaker | I116: 4 | J116: 2499 | K116: 0 | L116: Debit Card | M116: Delivered | N116: =Table1[[#This Row],[Quantity]]*Table1[[#This Row],[Unit Price (₹)]]*(1-Table1[[#This Row],[Discount %]]) -> 9996 | O116: =TEXT(Table1[[#This Row],[Order Date]],"mmmm") -> July | P116: =IF(Table1[[#This Row],[Revenue (₹) ← add]]>=15000,"High Value",IF(Table1[[#This Row],[Revenue (₹) ← add]]>=5000,"Medium","Low")) -> Medium | Q116: =VLOOKUP(Table1[[#This Row],[Product]],Table2[],4,FALSE) -> 1500 | R116: =Table1[[#This Row],[Revenue (₹) ← add]]-Table1[[#This Row],[Cost Price ← add]] -> 8496 | S116: =IF(C116="", "",Table1[[#This Row],[Delivery Date]]-Table1[[#This Row],[Order Date]]) -> 8 | T116: =TEXT(Table1[[#This Row],[Order Date]],"DDDD") -> Wednesday
...

Sheet Product_Master
A1: Product | B1: Category | C1: List Price (₹) | D1: Cost Price (₹)
A2: Wireless Mouse | B2: Electronics | C2: 799 | D2: 450
A3: Bluetooth Speaker | B3: Electronics | C3: 2499 | D3: 1500
A4: Headphones | B4: Electronics | C4: 1999 | D4: 1100
A5: Power Bank | B5: Electronics | C5: 1499 | D5: 850
A6: Office Chair | B6: Furniture | C6: 6999 | D6: 4200
A7: Study Desk | B7: Furniture | C7: 8499 | D7: 5200
A8: Bookshelf | B8: Furniture | C8: 5499 | D8: 3300
A9: Notebook Pack | B9: Stationery | C9: 349 | D9: 180
A10: Gel Pen Box | B10: Stationery | C10: 249 | D10: 120
A11: Desk Organizer | B11: Stationery | C11: 599 | D11: 320
A12: Cotton T-Shirt | B12: Clothing | C12: 599 | D12: 300
A13: Denim Jacket | B13: Clothing | C13: 2999 | D13: 1700
A15: Cost prices are illustrative sample inputs (blue = hardcoded input).

Sheet Targets
A1: Salesperson | B1: Region | C1: Annual Target (₹)
A2: Aarav Mehta | B2: North | C2: 170000
A3: Simran Kaur | B3: North | C3: 210000
A4: Karthik Iyer | B4: South | C4: 180000
A5: Meera Nair | B5: South | C5: 270000
A6: Rohit Das | B6: East | C6: 250000
A7: Ananya Sen | B7: East | C7: 190000
A8: Neha Joshi | B8: West | C8: 220000
A9: Vikram Shah | B9: West | C9: 270000
A12: Targets are illustrative sample inputs (blue = hardcoded).
A14: Salesperson | B14: Region | C14: Target | D14: Achieved | E14: Acheivement % | F14: Band | G14: Rank
A15: Aarav Mehta | B15: =INDEX(Table4[Region],MATCH(A15,$A$2:$A$9,0)) -> North | C15: =INDEX(Table4[Annual Target (₹)],MATCH(Table3[[#This Row],[Salesperson]],Table4[Salesperson],0)) -> 170000 | D15: {=SUMPRODUCT((Table1[Salesperson]=Table3[[#This Row],[Salesperson]])*Table1[Revenue (₹) ← add])} -> 172982.1 | E15: =D15/C15 -> 1.0175418 | F15: =IF(Table3[[#This Row],[Acheivement %]]>=100%,"Target Met",IF(Table3[[#This Row],[Acheivement %]]>=90%,"Close","Below Target")) -> Target Met | G15: =RANK(Table3[[#This Row],[Achieved]],Table3[Achieved]) -> 8
A16: Simran Kaur | B16: =INDEX(Table4[Region],MATCH(A16,$A$2:$A$9,0)) -> North | C16: =INDEX(Table4[Annual Target (₹)],MATCH(Table3[[#This Row],[Salesperson]],Table4[Salesperson],0)) -> 210000 | D16: {=SUMPRODUCT((Table1[Salesperson]=Table3[[#This Row],[Salesperson]])*Table1[Revenue (₹) ← add])} -> 195733.15 | E16: =D16/C16 -> 0.93206262 | F16: =IF(Table3[[#This Row],[Acheivement %]]>=100%,"Target Met",IF(Table3[[#This Row],[Acheivement %]]>=90%,"Close","Below Target")) -> Close | G16: =RANK(Table3[[#This Row],[Achieved]],Table3[Achieved]) -> 6
A17: Karthik Iyer | B17: =INDEX(Table4[Region],MATCH(A17,$A$2:$A$9,0)) -> South | C17: =INDEX(Table4[Annual Target (₹)],MATCH(Table3[[#This Row],[Salesperson]],Table4[Salesperson],0)) -> 180000 | D17: {=SUMPRODUCT((Table1[Salesperson]=Table3[[#This Row],[Salesperson]])*Table1[Revenue (₹) ← add])} -> 179666 | E17: =D17/C17 -> 0.99814444 | F17: =IF(Table3[[#This Row],[Acheivement %]]>=100%,"Target Met",IF(Table3[[#This Row],[Acheivement %]]>=90%,"Close","Below Target")) -> Close | G17: =RANK(Table3[[#This Row],[Achieved]],Table3[Achieved]) -> 7
A18: Meera Nair | B18: =INDEX(Table4[Region],MATCH(A18,$A$2:$A$9,0)) -> South | C18: =INDEX(Table4[Annual Target (₹)],MATCH(Table3[[#This Row],[Salesperson]],Table4[Salesperson],0)) -> 270000 | D18: {=SUMPRODUCT((Table1[Salesperson]=Table3[[#This Row],[Salesperson]])*Table1[Revenue (₹) ← add])} -> 260777.75 | E18: =D18/C18 -> 0.96584352 | F18: =IF(Table3[[#This Row],[Acheivement %]]>=100%,"Target Met",IF(Table3[[#This Row],[Acheivement %]]>=90%,"Close","Below Target")) -> Close | G18: =RANK(Table3[[#This Row],[Achieved]],Table3[Achieved]) -> 2
A19: Rohit Das | B19: =INDEX(Table4[Region],MATCH(A19,$A$2:$A$9,0)) -> East | C19: =INDEX(Table4[Annual Target (₹)],MATCH(Table3[[#This Row],[Salesperson]],Table4[Salesperson],0)) -> 250000 | D19: {=SUMPRODUCT((Table1[Salesperson]=Table3[[#This Row],[Salesperson]])*Table1[Revenue (₹) ← add])} -> 227080.6 | E19: =D19/C19 -> 0.9083224 | F19: =IF(Table3[[#This Row],[Acheivement %]]>=100%,"Target Met",IF(Table3[[#This Row],[Acheivement %]]>=90%,"Close","Below Target")) -> Close | G19: =RANK(Table3[[#This Row],[Achieved]],Table3[Achieved]) -> 3
A20: Ananya Sen | B20: =INDEX(Table4[Region],MATCH(A20,$A$2:$A$9,0)) -> East | C20: =INDEX(Table4[Annual Target (₹)],MATCH(Table3[[#This Row],[Salesperson]],Table4[Salesperson],0)) -> 190000 | D20: {=SUMPRODUCT((Table1[Salesperson]=Table3[[#This Row],[Salesperson]])*Table1[Revenue (₹) ← add])} -> 205298.6 | E20: =D20/C20 -> 1.0805189 | F20: =IF(Table3[[#This Row],[Acheivement %]]>=100%,"Target Met",IF(Table3[[#This Row],[Acheivement %]]>=90%,"Close","Below Target")) -> Target Met | G20: =RANK(Table3[[#This Row],[Achieved]],Table3[Achieved]) -> 5
A21: Neha Joshi | B21: =INDEX(Table4[Region],MATCH(A21,$A$2:$A$9,0)) -> West | C21: =INDEX(Table4[Annual Target (₹)],MATCH(Table3[[#This Row],[Salesperson]],Table4[Salesperson],0)) -> 220000 | D21: {=SUMPRODUCT((Table1[Salesperson]=Table3[[#This Row],[Salesperson]])*Table1[Revenue (₹) ← add])} -> 226843.55 | E21: =D21/C21 -> 1.031107 | F21: =IF(Table3[[#This Row],[Acheivement %]]>=100%,"Target Met",IF(Table3[[#This Row],[Acheivement %]]>=90%,"Close","Below Target")) -> Target Met | G21: =RANK(Table3[[#This Row],[Achieved]],Table3[Achieved]) -> 4
A22: Vikram Shah | B22: =INDEX(Table4[Region],MATCH(A22,$A$2:$A$9,0)) -> West | C22: =INDEX(Table4[Annual Target (₹)],MATCH(Table3[[#This Row],[Salesperson]],Table4[Salesperson],0)) -> 270000 | D22: {=SUMPRODUCT((Table1[Salesperson]=Table3[[#This Row],[Salesperson]])*Table1[Revenue (₹) ← add])} -> 279915.3 | E22: =D22/C22 -> 1.0367233 | F22: =IF(Table3[[#This Row],[Acheivement %]]>=100%,"Target Met",IF(Table3[[#This Row],[Acheivement %]]>=90%,"Close","Below Target")) -> Target Met | G22: =RANK(Table3[[#This Row],[Achieved]],Table3[Achieved]) -> 1
A24: Highest Revenue | B24: =INDEX(Table3[Salesperson],MATCH(MAX(Table3[Achieved]),Table3[Achieved],0)) -> Vikram Shah
A25: Salesperson who met target | B25: =COUNTIF(Table3[Band],"Target Met") -> 4
A27: MONTH NO | B27: MONTH | C27: REVENUE | D27: CUMULATIVE | E27: MOM GROWTH%
A28: {=_xlfn.UNIQUE(MONTH(Table1[Order Date]))} -> 1 | B28: =TEXT(DATE(2025,A28,1),"MMMM") -> January | C28: {=SUMPRODUCT((MONTH(Table1[Order Date])=A28)*Table1[Revenue (₹) ← add])} -> 126289.65 | D28: =SUM($C$28:C28) -> 126289.65
A29: 2 | B29: =TEXT(DATE(2025,A29,1),"MMMM") -> February | C29: {=SUMPRODUCT((MONTH(Table1[Order Date])=A29)*Table1[Revenue (₹) ← add])} -> 156453.7 | D29: =SUM($C$28:C29) -> 282743.35 | E29: =IF(C28=0,"",C29/C28-1) -> 0.23884816
A30: 3 | B30: =TEXT(DATE(2025,A30,1),"MMMM") -> March | C30: {=SUMPRODUCT((MONTH(Table1[Order Date])=A30)*Table1[Revenue (₹) ← add])} -> 96114.9 | D30: =SUM($C$28:C30) -> 378858.25 | E30: =IF(C29=0,"",C30/C29-1) -> -0.38566554
A31: 4 | B31: =TEXT(DATE(2025,A31,1),"MMMM") -> April | C31: {=SUMPRODUCT((MONTH(Table1[Order Date])=A31)*Table1[Revenue (₹) ← add])} -> 130723 | D31: =SUM($C$28:C31) -> 509581.25 | E31: =IF(C30=0,"",C31/C30-1) -> 0.36007008
A32: 5 | B32: =TEXT(DATE(2025,A32,1),"MMMM") -> May | C32: {=SUMPRODUCT((MONTH(Table1[Order Date])=A32)*Table1[Revenue (₹) ← add])} -> 196118.15 | D32: =SUM($C$28:C32) -> 705699.4 | E32: =IF(C31=0,"",C32/C31-1) -> 0.50025741
A33: 6 | B33: =TEXT(DATE(2025,A33,1),"MMMM") -> June | C33: {=SUMPRODUCT((MONTH(Table1[Order Date])=A33)*Table1[Revenue (₹) ← add])} -> 125040.2 | D33: =SUM($C$28:C33) -> 830739.6 | E33: =IF(C32=0,"",C33/C32-1) -> -0.36242413
A34: 7 | B34: =TEXT(DATE(2025,A34,1),"MMMM") -> July | C34: {=SUMPRODUCT((MONTH(Table1[Order Date])=A34)*Table1[Revenue (₹) ← add])} -> 156061.8 | D34: =SUM($C$28:C34) -> 986801.4 | E34: =IF(C33=0,"",C34/C33-1) -> 0.24809301
A35: 8 | B35: =TEXT(DATE(2025,A35,1),"MMMM") -> August | C35: {=SUMPRODUCT((MONTH(Table1[Order Date])=A35)*Table1[Revenue (₹) ← add])} -> 127977.45 | D35: =SUM($C$28:C35) -> 1114778.8 | E35: =IF(C34=0,"",C35/C34-1) -> -0.17995659
A36: 9 | B36: =TEXT(DATE(2025,A36,1),"MMMM") -> September | C36: {=SUMPRODUCT((MONTH(Table1[Order Date])=A36)*Table1[Revenue (₹) ← add])} -> 117795.75 | D36: =SUM($C$28:C36) -> 1232574.6 | E36: =IF(C35=0,"",C36/C35-1) -> -0.079558547
A37: 10 | B37: =TEXT(DATE(2025,A37,1),"MMMM") -> October | C37: {=SUMPRODUCT((MONTH(Table1[Order Date])=A37)*Table1[Revenue (₹) ← add])} -> 201285 | D37: =SUM($C$28:C37) -> 1433859.6 | E37: =IF(C36=0,"",C37/C36-1) -> 0.70876284
A38: 11 | B38: =TEXT(DATE(2025,A38,1),"MMMM") -> November | C38: {=SUMPRODUCT((MONTH(Table1[Order Date])=A38)*Table1[Revenue (₹) ← add])} -> 221801.75 | D38: =SUM($C$28:C38) -> 1655661.3 | E38: =IF(C37=0,"",C38/C37-1) -> 0.10192886
A39: 12 | B39: =TEXT(DATE(2025,A39,1),"MMMM") -> December | C39: {=SUMPRODUCT((MONTH(Table1[Order Date])=A39)*Table1[Revenue (₹) ← add])} -> 92635.7 | D39: =SUM($C$28:C39) -> 1748297 | E39: =IF(C38=0,"",C39/C38-1) -> -0.5823491
A40: TOTAL | C40: =SUM(C28:C39) -> 1748297
A43: CATEGORY | B43: {=TRANSPOSE(_xlfn.UNIQUE(Table1[Category]))} -> Stationery | C43: Clothing | D43: Furniture | E43: Electronics | F43: TOTAL
A44: {=_xlfn.UNIQUE(Table1[Region])} -> East | B44: {=SUMPRODUCT((Table1[Region]=$A44)*(Table1[Category]=B$43)*(Table1[Revenue (₹) ← add]))} -> 71245.2 | C44: {=SUMPRODUCT((Table1[Region]=$A44)*(Table1[Category]=C$43)*(Table1[Revenue (₹) ← add]))} -> 61774.15 | D44: {=SUMPRODUCT((Table1[Region]=$A44)*(Table1[Category]=D$43)*(Table1[Revenue (₹) ← add]))} -> 236589.75 | E44: {=SUMPRODUCT((Table1[Region]=$A44)*(Table1[Category]=E$43)*(Table1[Revenue (₹) ← add]))} -> 62770.1 | F44: =SUM(B44:E44) -> 432379.2
A45: South | B45: {=SUMPRODUCT((Table1[Region]=$A45)*(Table1[Category]=B$43)*(Table1[Revenue (₹) ← add]))} -> 67573.15 | C45: {=SUMPRODUCT((Table1[Region]=$A45)*(Table1[Category]=C$43)*(Table1[Revenue (₹) ← add]))} -> 54941.55 | D45: {=SUMPRODUCT((Table1[Region]=$A45)*(Table1[Category]=D$43)*(Table1[Revenue (₹) ← add]))} -> 167274.6 | E45: {=SUMPRODUCT((Table1[Region]=$A45)*(Table1[Category]=E$43)*(Table1[Revenue (₹) ← add]))} -> 150654.45 | F45: =SUM(B45:E45) -> 440443.75
A46: North | B46: {=SUMPRODUCT((Table1[Region]=$A46)*(Table1[Category]=B$43)*(Table1[Revenue (₹) ← add]))} -> 56599.95 | C46: {=SUMPRODUCT((Table1[Region]=$A46)*(Table1[Category]=C$43)*(Table1[Revenue (₹) ← add]))} -> 58277 | D46: {=SUMPRODUCT((Table1[Region]=$A46)*(Table1[Category]=D$43)*(Table1[Revenue (₹) ← add]))} -> 155377.5 | E46: {=SUMPRODUCT((Table1[Region]=$A46)*(Table1[Category]=E$43)*(Table1[Revenue (₹) ← add]))} -> 98460.8 | F46: =SUM(B46:E46) -> 368715.25
A47: West | B47: {=SUMPRODUCT((Table1[Region]=$A47)*(Table1[Category]=B$43)*(Table1[Revenue (₹) ← add]))} -> 65183.65 | C47: {=SUMPRODUCT((Table1[Region]=$A47)*(Table1[Category]=C$43)*(Table1[Revenue (₹) ← add]))} -> 71596 | D47: {=SUMPRODUCT((Table1[Region]=$A47)*(Table1[Category]=D$43)*(Table1[Revenue (₹) ← add]))} -> 211945.5 | E47: {=SUMPRODUCT((Table1[Region]=$A47)*(Table1[Category]=E$43)*(Table1[Revenue (₹) ← add]))} -> 158033.7 | F47: =SUM(B47:E47) -> 506758.85
A48: TOTAL | B48: =SUM(B44:B47) -> 260601.95 | C48: =SUM(C44:C47) -> 246588.7 | D48: =SUM(D44:D47) -> 771187.35 | E48: =SUM(E44:E47) -> 469919.05 | F48: =SUM(F44:F47) -> 1748297
A50: Share of total | B50: =B48/$F$48 -> 0.14906045 | C50: =C48/$F$48 -> 0.14104508 | D50: =D48/$F$48 -> 0.44110773 | E50: =E48/$F$48 -> 0.26878673
A52: RANK | B52: SALESPERSON | C52: REVENUE
A53: 1 | B53: =INDEX(A15:A22,MATCH(LARGE(D15:D22,A53),D15:D22,0)) -> Vikram Shah | C53: {=INDEX(Table3[Achieved],MATCH(B53:B55,Table3[Salesperson],0))} -> 279915.3
A54: 2 | B54: =INDEX(Table4[Salesperson],MATCH(LARGE(Table4[Annual Target (₹)],A54),Table4[Annual Target (₹)],0)) -> Meera Nair | C54: 260777.75
A55: 3 | B55: =INDEX(Table4[Salesperson],MATCH(LARGE(Table4[Annual Target (₹)],A55),Table4[Annual Target (₹)],0)) -> Rohit Das | C55: 227080.6
A57: no of unique CITIES | B57: {=SUMPRODUCT(1/COUNTIF(Table1[City],Table1[City]))} -> 12 | C57: =COUNTA(_xlfn.UNIQUE(Table1[City])) -> 12

Sheet Dashboard
A2: Region | B2: Revenue | C2: Orders | D2: Avg discount | E2: Return rate
A3: West | B3: =SUMIF(Table1[Region],A3,Table1[Revenue (₹) ← add]) -> 506758.85 | C3: =COUNTIF(Table1[Region],A3) -> 65 | D3: =AVERAGEIF(Table1[Region],A3,Table1[Discount %]) -> 0.072307692 | E3: =(COUNTIFS(Table1[Region],A3,Table1[Status],"Returned")/COUNTIF(Table1[Status],"Returned")) -> 0.4 | J3: {=_xlfn.UNIQUE(Table1[Region])} -> East
J4: South
J5: North
J6: West
A7: Count of Revenue (₹) ← add | B7: Column Labels
A8: Row Labels | B8: Clothing | C8: Electronics | D8: Furniture | E8: Stationery | F8: Grand Total
A9: East | B9: 3 | C9: 1 | D9: 1 | E9: 2 | F9: 7
A10: North | B10: 1 | D10: 1 | E10: 3 | F10: 5
A11: South | B11: 1 | C11: 4 | D11: 1 | E11: 4 | F11: 10
A12: West | B12: 1 | C12: 5 | D12: 2 | E12: 3 | F12: 11
A13: Grand Total | B13: 6 | C13: 10 | D13: 5 | E13: 12 | F13: 33

Sheet Messy_Data
A1: Customer Name | B1: Phone | C1: City | D1: Order Amount
A2: Riya Sharma | B2: 9876543210 | C2: Mumbai | D2: 1250
A3: Amit Verma | B3: 9876543211 | C3: Mumbai | D3: 2999
A4: Priya Nair | B4: 9876543212 | C4: Pune | D4: 850
A5: Riya Sharma | B5: 9876543210 | C5: Pune | D5: 1499
A6: Karan Mehta | B6: 9876543213 | C6: Delhi | D6: 3450
A7: Sneha Iyer | B7: 9876543214 | C7: Delhi | D7: 599
A8: Amit Verma | B8: 9876543211 | C8: Lucknow | D8: 1250
A9: Rahul Das | B9: 9876543215 | C9: Lucknow | D9: 2100
A10: Neha Joshi | B10: 9876543216 | C10: Mumbai | D10: 799
A11: Karan Mehta | B11: 9876543213 | C11: Delhi | D11: 1999
A12: Vikram Shah | B12: 9876543217 | C12: Pune | D12: 4200
A13: Ananya Sen | B13: 9876543218 | C13: Delhi | D13: 649
A15: Unique_cutsomer | B15: =COUNTA(_xlfn.UNIQUE(A2:A13)) -> 9 | D15: =SUM(D2:D13) -> 21644
A16: sum_product | B16: {=SUMPRODUCT(1/COUNTIF(A2:A13,A2:A13))} -> 9 | C16: {=COUNTIF(A2:A13,A2:A13)} -> 2
C17: 2
C18: 1
C19: 2
C20: 2
C21: 1
C22: 2
C23: 1
C24: 1
C25: 2
C26: 1
C27: 1

Sheet Answer_Tables
A1: A. Salesperson performance (Q16, Q17, Q21)
A2: Salesperson | B2: Region | C2: Revenue | D2: Target | E2: Achievement % | F2: Band | G2: Rank
A3: =Targets!A2 -> Aarav Mehta | B3: =INDEX(Targets!$B$2:$B$9,MATCH(A3,Targets!$A$2:$A$9,0)) -> North | C3: =SUMPRODUCT((Sales_Data!$F$2:$F$251=A3)*Sales_Data!$I$2:$I$251*Sales_Data!$J$2:$J$251*(1-Sales_Data!$K$2:$K$251)) -> 172982.1 | D3: =INDEX(Targets!$C$2:$C$9,MATCH(A3,Targets!$A$2:$A$9,0)) -> 170000 | E3: =C3/D3 -> 1.0175418 | F3: =IF(E3>=1,"Target Met",IF(E3>=0.9,"Close","Below Target")) -> Target Met | G3: =RANK(C3,$C$3:$C$10) -> 8
A4: =Targets!A3 -> Simran Kaur | B4: =INDEX(Targets!$B$2:$B$9,MATCH(A4,Targets!$A$2:$A$9,0)) -> North | C4: =SUMPRODUCT((Sales_Data!$F$2:$F$251=A4)*Sales_Data!$I$2:$I$251*Sales_Data!$J$2:$J$251*(1-Sales_Data!$K$2:$K$251)) -> 195733.15 | D4: =INDEX(Targets!$C$2:$C$9,MATCH(A4,Targets!$A$2:$A$9,0)) -> 210000 | E4: =C4/D4 -> 0.93206262 | F4: =IF(E4>=1,"Target Met",IF(E4>=0.9,"Close","Below Target")) -> Close | G4: =RANK(C4,$C$3:$C$10) -> 6
A5: =Targets!A4 -> Karthik Iyer | B5: =INDEX(Targets!$B$2:$B$9,MATCH(A5,Targets!$A$2:$A$9,0)) -> South | C5: =SUMPRODUCT((Sales_Data!$F$2:$F$251=A5)*Sales_Data!$I$2:$I$251*Sales_Data!$J$2:$J$251*(1-Sales_Data!$K$2:$K$251)) -> 179666 | D5: =INDEX(Targets!$C$2:$C$9,MATCH(A5,Targets!$A$2:$A$9,0)) -> 180000 | E5: =C5/D5 -> 0.99814444 | F5: =IF(E5>=1,"Target Met",IF(E5>=0.9,"Close","Below Target")) -> Close | G5: =RANK(C5,$C$3:$C$10) -> 7
A6: =Targets!A5 -> Meera Nair | B6: =INDEX(Targets!$B$2:$B$9,MATCH(A6,Targets!$A$2:$A$9,0)) -> South | C6: =SUMPRODUCT((Sales_Data!$F$2:$F$251=A6)*Sales_Data!$I$2:$I$251*Sales_Data!$J$2:$J$251*(1-Sales_Data!$K$2:$K$251)) -> 260777.75 | D6: =INDEX(Targets!$C$2:$C$9,MATCH(A6,Targets!$A$2:$A$9,0)) -> 270000 | E6: =C6/D6 -> 0.96584352 | F6: =IF(E6>=1,"Target Met",IF(E6>=0.9,"Close","Below Target")) -> Close | G6: =RANK(C6,$C$3:$C$10) -> 2
A7: =Targets!A6 -> Rohit Das | B7: =INDEX(Targets!$B$2:$B$9,MATCH(A7,Targets!$A$2:$A$9,0)) -> East | C7: =SUMPRODUCT((Sales_Data!$F$2:$F$251=A7)*Sales_Data!$I$2:$I$251*Sales_Data!$J$2:$J$251*(1-Sales_Data!$K$2:$K$251)) -> 227080.6 | D7: =INDEX(Targets!$C$2:$C$9,MATCH(A7,Targets!$A$2:$A$9,0)) -> 250000 | E7: =C7/D7 -> 0.9083224 | F7: =IF(E7>=1,"Target Met",IF(E7>=0.9,"Close","Below Target")) -> Close | G7: =RANK(C7,$C$3:$C$10) -> 3
A8: =Targets!A7 -> Ananya Sen | B8: =INDEX(Targets!$B$2:$B$9,MATCH(A8,Targets!$A$2:$A$9,0)) -> East | C8: =SUMPRODUCT((Sales_Data!$F$2:$F$251=A8)*Sales_Data!$I$2:$I$251*Sales_Data!$J$2:$J$251*(1-Sales_Data!$K$2:$K$251)) -> 205298.6 | D8: =INDEX(Targets!$C$2:$C$9,MATCH(A8,Targets!$A$2:$A$9,0)) -> 190000 | E8: =C8/D8 -> 1.0805189 | F8: =IF(E8>=1,"Target Met",IF(E8>=0.9,"Close","Below Target")) -> Target Met | G8: =RANK(C8,$C$3:$C$10) -> 5
A9: =Targets!A8 -> Neha Joshi | B9: =INDEX(Targets!$B$2:$B$9,MATCH(A9,Targets!$A$2:$A$9,0)) -> West | C9: =SUMPRODUCT((Sales_Data!$F$2:$F$251=A9)*Sales_Data!$I$2:$I$251*Sales_Data!$J$2:$J$251*(1-Sales_Data!$K$2:$K$251)) -> 226843.55 | D9: =INDEX(Targets!$C$2:$C$9,MATCH(A9,Targets!$A$2:$A$9,0)) -> 220000 | E9: =C9/D9 -> 1.031107 | F9: =IF(E9>=1,"Target Met",IF(E9>=0.9,"Close","Below Target")) -> Target Met | G9: =RANK(C9,$C$3:$C$10) -> 4
A10: =Targets!A9 -> Vikram Shah | B10: =INDEX(Targets!$B$2:$B$9,MATCH(A10,Targets!$A$2:$A$9,0)) -> West | C10: =SUMPRODUCT((Sales_Data!$F$2:$F$251=A10)*Sales_Data!$I$2:$I$251*Sales_Data!$J$2:$J$251*(1-Sales_Data!$K$2:$K$251)) -> 279915.3 | D10: =INDEX(Targets!$C$2:$C$9,MATCH(A10,Targets!$A$2:$A$9,0)) -> 270000 | E10: =C10/D10 -> 1.0367233 | F10: =IF(E10>=1,"Target Met",IF(E10>=0.9,"Close","Below Target")) -> Target Met | G10: =RANK(C10,$C$3:$C$10) -> 1
A12: Top salesperson | B12: =INDEX(A3:A10,MATCH(MAX(C3:C10),C3:C10,0)) -> Vikram Shah
A14: Top 3 salespeople (Q21)
A15: Rank | B15: Salesperson | C15: Revenue
A16: 1 | B16: =INDEX($A$3:$A$10,MATCH(LARGE($C$3:$C$10,A16),$C$3:$C$10,0)) -> Vikram Shah | C16: =LARGE($C$3:$C$10,A16) -> 279915.3
A17: 2 | B17: =INDEX($A$3:$A$10,MATCH(LARGE($C$3:$C$10,A17),$C$3:$C$10,0)) -> Meera Nair | C17: =LARGE($C$3:$C$10,A17) -> 260777.75
A18: 3 | B18: =INDEX($A$3:$A$10,MATCH(LARGE($C$3:$C$10,A18),$C$3:$C$10,0)) -> Rohit Das | C18: =LARGE($C$3:$C$10,A18) -> 227080.6
A21: B. Monthly revenue, cumulative & MoM growth (Q18)
A22: Month No | B22: Month | C22: Revenue | D22: Cumulative | E22: MoM Growth %
A23: 1 | B23: =TEXT(DATE(2025,A23,1),"mmm") -> Jan | C23: =SUMPRODUCT((MONTH(Sales_Data!$B$2:$B$251)=A23)*Sales_Data!$I$2:$I$251*Sales_Data!$J$2:$J$251*(1-Sales_Data!$K$2:$K$251)) -> 126289.65 | D23: =SUM($C$23:C23) -> 126289.65
A24: 2 | B24: =TEXT(DATE(2025,A24,1),"mmm") -> Feb | C24: =SUMPRODUCT((MONTH(Sales_Data!$B$2:$B$251)=A24)*Sales_Data!$I$2:$I$251*Sales_Data!$J$2:$J$251*(1-Sales_Data!$K$2:$K$251)) -> 156453.7 | D24: =SUM($C$23:C24) -> 282743.35 | E24: =IF(C23=0,"",C24/C23-1) -> 0.23884816
A25: 3 | B25: =TEXT(DATE(2025,A25,1),"mmm") -> Mar | C25: =SUMPRODUCT((MONTH(Sales_Data!$B$2:$B$251)=A25)*Sales_Data!$I$2:$I$251*Sales_Data!$J$2:$J$251*(1-Sales_Data!$K$2:$K$251)) -> 96114.9 | D25: =SUM($C$23:C25) -> 378858.25 | E25: =IF(C24=0,"",C25/C24-1) -> -0.38566554
A26: 4 | B26: =TEXT(DATE(2025,A26,1),"mmm") -> Apr | C26: =SUMPRODUCT((MONTH(Sales_Data!$B$2:$B$251)=A26)*Sales_Data!$I$2:$I$251*Sales_Data!$J$2:$J$251*(1-Sales_Data!$K$2:$K$251)) -> 130723 | D26: =SUM($C$23:C26) -> 509581.25 | E26: =IF(C25=0,"",C26/C25-1) -> 0.36007008
A27: 5 | B27: =TEXT(DATE(2025,A27,1),"mmm") -> May | C27: =SUMPRODUCT((MONTH(Sales_Data!$B$2:$B$251)=A27)*Sales_Data!$I$2:$I$251*Sales_Data!$J$2:$J$251*(1-Sales_Data!$K$2:$K$251)) -> 196118.15 | D27: =SUM($C$23:C27) -> 705699.4 | E27: =IF(C26=0,"",C27/C26-1) -> 0.50025741
A28: 6 | B28: =TEXT(DATE(2025,A28,1),"mmm") -> Jun | C28: =SUMPRODUCT((MONTH(Sales_Data!$B$2:$B$251)=A28)*Sales_Data!$I$2:$I$251*Sales_Data!$J$2:$J$251*(1-Sales_Data!$K$2:$K$251)) -> 125040.2 | D28: =SUM($C$23:C28) -> 830739.6 | E28: =IF(C27=0,"",C28/C27-1) -> -0.36242413
A29: 7 | B29: =TEXT(DATE(2025,A29,1),"mmm") -> Jul | C29: =SUMPRODUCT((MONTH(Sales_Data!$B$2:$B$251)=A29)*Sales_Data!$I$2:$I$251*Sales_Data!$J$2:$J$251*(1-Sales_Data!$K$2:$K$251)) -> 156061.8 | D29: =SUM($C$23:C29) -> 986801.4 | E29: =IF(C28=0,"",C29/C28-1) -> 0.24809301
A30: 8 | B30: =TEXT(DATE(2025,A30,1),"mmm") -> Aug | C30: =SUMPRODUCT((MONTH(Sales_Data!$B$2:$B$251)=A30)*Sales_Data!$I$2:$I$251*Sales_Data!$J$2:$J$251*(1-Sales_Data!$K$2:$K$251)) -> 127977.45 | D30: =SUM($C$23:C30) -> 1114778.8 | E30: =IF(C29=0,"",C30/C29-1) -> -0.17995659
A31: 9 | B31: =TEXT(DATE(2025,A31,1),"mmm") -> Sep | C31: =SUMPRODUCT((MONTH(Sales_Data!$B$2:$B$251)=A31)*Sales_Data!$I$2:$I$251*Sales_Data!$J$2:$J$251*(1-Sales_Data!$K$2:$K$251)) -> 117795.75 | D31: =SUM($C$23:C31) -> 1232574.6 | E31: =IF(C30=0,"",C31/C30-1) -> -0.079558547
A32: 10 | B32: =TEXT(DATE(2025,A32,1),"mmm") -> Oct | C32: =SUMPRODUCT((MONTH(Sales_Data!$B$2:$B$251)=A32)*Sales_Data!$I$2:$I$251*Sales_Data!$J$2:$J$251*(1-Sales_Data!$K$2:$K$251)) -> 201285 | D32: =SUM($C$23:C32) -> 1433859.6 | E32: =IF(C31=0,"",C32/C31-1) -> 0.70876284
A33: 11 | B33: =TEXT(DATE(2025,A33,1),"mmm") -> Nov | C33: =SUMPRODUCT((MONTH(Sales_Data!$B$2:$B$251)=A33)*Sales_Data!$I$2:$I$251*Sales_Data!$J$2:$J$251*(1-Sales_Data!$K$2:$K$251)) -> 221801.75 | D33: =SUM($C$23:C33) -> 1655661.3 | E33: =IF(C32=0,"",C33/C32-1) -> 0.10192886
A34: 12 | B34: =TEXT(DATE(2025,A34,1),"mmm") -> Dec | C34: =SUMPRODUCT((MONTH(Sales_Data!$B$2:$B$251)=A34)*Sales_Data!$I$2:$I$251*Sales_Data!$J$2:$J$251*(1-Sales_Data!$K$2:$K$251)) -> 92635.7 | D34: =SUM($C$23:C34) -> 1748297 | E34: =IF(C33=0,"",C34/C33-1) -> -0.5823491
A35: Total | C35: =SUM(C23:C34) -> 1748297
A38: C. Region × Category revenue (pivot check) (Q19, Q20, Q23)
A39: Region | B39: Electronics | C39: Furniture | D39: Stationery | E39: Clothing | F39: Total
A40: North | B40: =SUMPRODUCT((Sales_Data!$D$2:$D$251=$A40)*(Sales_Data!$G$2:$G$251=B$39)*Sales_Data!$I$2:$I$251*Sales_Data!$J$2:$J$251*(1-Sales_Data!$K$2:$K$251)) -> 98460.8 | C40: =SUMPRODUCT((Sales_Data!$D$2:$D$251=$A40)*(Sales_Data!$G$2:$G$251=C$39)*Sales_Data!$I$2:$I$251*Sales_Data!$J$2:$J$251*(1-Sales_Data!$K$2:$K$251)) -> 155377.5 | D40: =SUMPRODUCT((Sales_Data!$D$2:$D$251=$A40)*(Sales_Data!$G$2:$G$251=D$39)*Sales_Data!$I$2:$I$251*Sales_Data!$J$2:$J$251*(1-Sales_Data!$K$2:$K$251)) -> 56599.95 | E40: =SUMPRODUCT((Sales_Data!$D$2:$D$251=$A40)*(Sales_Data!$G$2:$G$251=E$39)*Sales_Data!$I$2:$I$251*Sales_Data!$J$2:$J$251*(1-Sales_Data!$K$2:$K$251)) -> 58277 | F40: =SUM(B40:E40) -> 368715.25
A41: South | B41: =SUMPRODUCT((Sales_Data!$D$2:$D$251=$A41)*(Sales_Data!$G$2:$G$251=B$39)*Sales_Data!$I$2:$I$251*Sales_Data!$J$2:$J$251*(1-Sales_Data!$K$2:$K$251)) -> 150654.45 | C41: =SUMPRODUCT((Sales_Data!$D$2:$D$251=$A41)*(Sales_Data!$G$2:$G$251=C$39)*Sales_Data!$I$2:$I$251*Sales_Data!$J$2:$J$251*(1-Sales_Data!$K$2:$K$251)) -> 167274.6 | D41: =SUMPRODUCT((Sales_Data!$D$2:$D$251=$A41)*(Sales_Data!$G$2:$G$251=D$39)*Sales_Data!$I$2:$I$251*Sales_Data!$J$2:$J$251*(1-Sales_Data!$K$2:$K$251)) -> 67573.15 | E41: =SUMPRODUCT((Sales_Data!$D$2:$D$251=$A41)*(Sales_Data!$G$2:$G$251=E$39)*Sales_Data!$I$2:$I$251*Sales_Data!$J$2:$J$251*(1-Sales_Data!$K$2:$K$251)) -> 54941.55 | F41: =SUM(B41:E41) -> 440443.75
A42: East | B42: =SUMPRODUCT((Sales_Data!$D$2:$D$251=$A42)*(Sales_Data!$G$2:$G$251=B$39)*Sales_Data!$I$2:$I$251*Sales_Data!$J$2:$J$251*(1-Sales_Data!$K$2:$K$251)) -> 62770.1 | C42: =SUMPRODUCT((Sales_Data!$D$2:$D$251=$A42)*(Sales_Data!$G$2:$G$251=C$39)*Sales_Data!$I$2:$I$251*Sales_Data!$J$2:$J$251*(1-Sales_Data!$K$2:$K$251)) -> 236589.75 | D42: =SUMPRODUCT((Sales_Data!$D$2:$D$251=$A42)*(Sales_Data!$G$2:$G$251=D$39)*Sales_Data!$I$2:$I$251*Sales_Data!$J$2:$J$251*(1-Sales_Data!$K$2:$K$251)) -> 71245.2 | E42: =SUMPRODUCT((Sales_Data!$D$2:$D$251=$A42)*(Sales_Data!$G$2:$G$251=E$39)*Sales_Data!$I$2:$I$251*Sales_Data!$J$2:$J$251*(1-Sales_Data!$K$2:$K$251)) -> 61774.15 | F42: =SUM(B42:E42) -> 432379.2
A43: West | B43: =SUMPRODUCT((Sales_Data!$D$2:$D$251=$A43)*(Sales_Data!$G$2:$G$251=B$39)*Sales_Data!$I$2:$I$251*Sales_Data!$J$2:$J$251*(1-Sales_Data!$K$2:$K$251)) -> 158033.7 | C43: =SUMPRODUCT((Sales_Data!$D$2:$D$251=$A43)*(Sales_Data!$G$2:$G$251=C$39)*Sales_Data!$I$2:$I$251*Sales_Data!$J$2:$J$251*(1-Sales_Data!$K$2:$K$251)) -> 211945.5 | D43: =SUMPRODUCT((Sales_Data!$D$2:$D$251=$A43)*(Sales_Data!$G$2:$G$251=D$39)*Sales_Data!$I$2:$I$251*Sales_Data!$J$2:$J$251*(1-Sales_Data!$K$2:$K$251)) -> 65183.65 | E43: =SUMPRODUCT((Sales_Data!$D$2:$D$251=$A43)*(Sales_Data!$G$2:$G$251=E$39)*Sales_Data!$I$2:$I$251*Sales_Data!$J$2:$J$251*(1-Sales_Data!$K$2:$K$251)) -> 71596 | F43: =SUM(B43:E43) -> 506758.85
A44: Total | B44: =SUM(B40:B43) -> 469919.05 | C44: =SUM(C40:C43) -> 771187.35 | D44: =SUM(D40:D43) -> 260601.95 | E44: =SUM(E40:E43) -> 246588.7 | F44: =SUM(F40:F43) -> 1748297
A47: Share of total | B47: =B44/$F$44 -> 0.26878673 | C47: =C44/$F$44 -> 0.44110773 | D47: =D44/$F$44 -> 0.14906045 | E47: =E44/$F$44 -> 0.14104508
A50: D. Return rate by category (Q13)
A51: Category | B51: Orders | C51: Returned | D51: Return %
A52: Electronics | B52: =COUNTIF(Sales_Data!$G$2:$G$251,A52) -> 84 | C52: =COUNTIFS(Sales_Data!$G$2:$G$251,A52,Sales_Data!$M$2:$M$251,"Returned") -> 5 | D52: =C52/B52 -> 0.05952381
A53: Furniture | B53: =COUNTIF(Sales_Data!$G$2:$G$251,A53) -> 55 | C53: =COUNTIFS(Sales_Data!$G$2:$G$251,A53,Sales_Data!$M$2:$M$251,"Returned") -> 1 | D53: =C53/B53 -> 0.018181818
A54: Stationery | B54: =COUNTIF(Sales_Data!$G$2:$G$251,A54) -> 59 | C54: =COUNTIFS(Sales_Data!$G$2:$G$251,A54,Sales_Data!$M$2:$M$251,"Returned") -> 7 | D54: =C54/B54 -> 0.11864407
A55: Clothing | B55: =COUNTIF(Sales_Data!$G$2:$G$251,A55) -> 52 | C55: =COUNTIFS(Sales_Data!$G$2:$G$251,A55,Sales_Data!$M$2:$M$251,"Returned") -> 2 | D55: =C55/B55 -> 0.038461538
A58: E. Cleaned Messy_Data (Q26–Q30)
A59: Clean Name | B59: First Name | C59: Phone (10 digits) | D59: City | E59: Amount (₹)
A60: =PROPER(TRIM(Messy_Data!A2)) -> Riya Sharma | B60: =LEFT(A60,FIND(" ",A60)-1) -> Riya | C60: =RIGHT(SUBSTITUTE(SUBSTITUTE(SUBSTITUTE(TRIM(Messy_Data!B2)," ",""),"-",""),"+",""),10) -> 9876543210 | D60: =PROPER(TRIM(Messy_Data!C2)) -> Mumbai | E60: =VALUE(SUBSTITUTE(SUBSTITUTE(SUBSTITUTE(SUBSTITUTE(Messy_Data!D2,"₹",""),"Rs.","")," ",""),",","")) -> 1250
A61: =PROPER(TRIM(Messy_Data!A3)) -> Amit Verma | B61: =LEFT(A61,FIND(" ",A61)-1) -> Amit | C61: =RIGHT(SUBSTITUTE(SUBSTITUTE(SUBSTITUTE(TRIM(Messy_Data!B3)," ",""),"-",""),"+",""),10) -> 9876543211 | D61: =PROPER(TRIM(Messy_Data!C3)) -> Mumbai | E61: =VALUE(SUBSTITUTE(SUBSTITUTE(SUBSTITUTE(SUBSTITUTE(Messy_Data!D3,"₹",""),"Rs.","")," ",""),",","")) -> 2999
A62: =PROPER(TRIM(Messy_Data!A4)) -> Priya Nair | B62: =LEFT(A62,FIND(" ",A62)-1) -> Priya | C62: =RIGHT(SUBSTITUTE(SUBSTITUTE(SUBSTITUTE(TRIM(Messy_Data!B4)," ",""),"-",""),"+",""),10) -> 9876543212 | D62: =PROPER(TRIM(Messy_Data!C4)) -> Pune | E62: =VALUE(SUBSTITUTE(SUBSTITUTE(SUBSTITUTE(SUBSTITUTE(Messy_Data!D4,"₹",""),"Rs.","")," ",""),",","")) -> 850
A63: =PROPER(TRIM(Messy_Data!A5)) -> Riya Sharma | B63: =LEFT(A63,FIND(" ",A63)-1) -> Riya | C63: =RIGHT(SUBSTITUTE(SUBSTITUTE(SUBSTITUTE(TRIM(Messy_Data!B5)," ",""),"-",""),"+",""),10) -> 9876543210 | D63: =PROPER(TRIM(Messy_Data!C5)) -> Pune | E63: =VALUE(SUBSTITUTE(SUBSTITUTE(SUBSTITUTE(SUBSTITUTE(Messy_Data!D5,"₹",""),"Rs.","")," ",""),",","")) -> 1499
A64: =PROPER(TRIM(Messy_Data!A6)) -> Karan Mehta | B64: =LEFT(A64,FIND(" ",A64)-1) -> Karan | C64: =RIGHT(SUBSTITUTE(SUBSTITUTE(SUBSTITUTE(TRIM(Messy_Data!B6)," ",""),"-",""),"+",""),10) -> 9876543213 | D64: =PROPER(TRIM(Messy_Data!C6)) -> Delhi | E64: =VALUE(SUBSTITUTE(SUBSTITUTE(SUBSTITUTE(SUBSTITUTE(Messy_Data!D6,"₹",""),"Rs.","")," ",""),",","")) -> 3450
A65: =PROPER(TRIM(Messy_Data!A7)) -> Sneha Iyer | B65: =LEFT(A65,FIND(" ",A65)-1) -> Sneha | C65: =RIGHT(SUBSTITUTE(SUBSTITUTE(SUBSTITUTE(TRIM(Messy_Data!B7)," ",""),"-",""),"+",""),10) -> 9876543214 | D65: =PROPER(TRIM(Messy_Data!C7)) -> Delhi | E65: =VALUE(SUBSTITUTE(SUBSTITUTE(SUBSTITUTE(SUBSTITUTE(Messy_Data!D7,"₹",""),"Rs.","")," ",""),",","")) -> 599
A66: =PROPER(TRIM(Messy_Data!A8)) -> Amit Verma | B66: =LEFT(A66,FIND(" ",A66)-1) -> Amit | C66: =RIGHT(SUBSTITUTE(SUBSTITUTE(SUBSTITUTE(TRIM(Messy_Data!B8)," ",""),"-",""),"+",""),10) -> 9876543211 | D66: =PROPER(TRIM(Messy_Data!C8)) -> Lucknow | E66: =VALUE(SUBSTITUTE(SUBSTITUTE(SUBSTITUTE(SUBSTITUTE(Messy_Data!D8,"₹",""),"Rs.","")," ",""),",","")) -> 1250
A67: =PROPER(TRIM(Messy_Data!A9)) -> Rahul Das | B67: =LEFT(A67,FIND(" ",A67)-1) -> Rahul | C67: =RIGHT(SUBSTITUTE(SUBSTITUTE(SUBSTITUTE(TRIM(Messy_Data!B9)," ",""),"-",""),"+",""),10) -> 9876543215 | D67: =PROPER(TRIM(Messy_Data!C9)) -> Lucknow | E67: =VALUE(SUBSTITUTE(SUBSTITUTE(SUBSTITUTE(SUBSTITUTE(Messy_Data!D9,"₹",""),"Rs.","")," ",""),",","")) -> 2100
A68: =PROPER(TRIM(Messy_Data!A10)) -> Neha Joshi | B68: =LEFT(A68,FIND(" ",A68)-1) -> Neha | C68: =RIGHT(SUBSTITUTE(SUBSTITUTE(SUBSTITUTE(TRIM(Messy_Data!B10)," ",""),"-",""),"+",""),10) -> 9876543216 | D68: =PROPER(TRIM(Messy_Data!C10)) -> Mumbai | E68: =VALUE(SUBSTITUTE(SUBSTITUTE(SUBSTITUTE(SUBSTITUTE(Messy_Data!D10,"₹",""),"Rs.","")," ",""),",","")) -> 799
A69: =PROPER(TRIM(Messy_Data!A11)) -> Karan Mehta | B69: =LEFT(A69,FIND(" ",A69)-1) -> Karan | C69: =RIGHT(SUBSTITUTE(SUBSTITUTE(SUBSTITUTE(TRIM(Messy_Data!B11)," ",""),"-",""),"+",""),10) -> 9876543213 | D69: =PROPER(TRIM(Messy_Data!C11)) -> Delhi | E69: =VALUE(SUBSTITUTE(SUBSTITUTE(SUBSTITUTE(SUBSTITUTE(Messy_Data!D11,"₹",""),"Rs.","")," ",""),",","")) -> 1999
A70: =PROPER(TRIM(Messy_Data!A12)) -> Vikram Shah | B70: =LEFT(A70,FIND(" ",A70)-1) -> Vikram | C70: =RIGHT(SUBSTITUTE(SUBSTITUTE(SUBSTITUTE(TRIM(Messy_Data!B12)," ",""),"-",""),"+",""),10) -> 9876543217 | D70: =PROPER(TRIM(Messy_Data!C12)) -> Pune | E70: =VALUE(SUBSTITUTE(SUBSTITUTE(SUBSTITUTE(SUBSTITUTE(Messy_Data!D12,"₹",""),"Rs.","")," ",""),",","")) -> 4200
A71: =PROPER(TRIM(Messy_Data!A13)) -> Ananya Sen | B71: =LEFT(A71,FIND(" ",A71)-1) -> Ananya | C71: =RIGHT(SUBSTITUTE(SUBSTITUTE(SUBSTITUTE(TRIM(Messy_Data!B13)," ",""),"-",""),"+",""),10) -> 9876543218 | D71: =PROPER(TRIM(Messy_Data!C13)) -> Delhi | E71: =VALUE(SUBSTITUTE(SUBSTITUTE(SUBSTITUTE(SUBSTITUTE(Messy_Data!D13,"₹",""),"Rs.","")," ",""),",","")) -> 649
A73: Unique customers | B73: {=SUMPRODUCT(1/COUNTIF(A60:A71,A60:A71))} -> 9
A74: Total amount | E74: =SUM(E60:E71) -> 21644

Sheet Answer_Key
A1: Q# | B1: What it answers | C1: Answer (live) | D1: Formula used | E1: Note
A2: 1 | B2: Grand total revenue | C2: =SUMPRODUCT(Sales_Data!$I$2:$I$251*Sales_Data!$J$2:$J$251*(1-Sales_Data!$K$2:$K$251)) -> 1748297.1 | D2: =SUMPRODUCT(Sales_Data!$I$2:$I$251*Sales_Data!$J$2:$J$251*(1-Sales_Data!$K$2:$K$251)) | E2: Your column N total should match
A3: 2a | B3: Total orders | C3: =COUNTA(Sales_Data!$A$2:$A$251) -> 250 | D3: =COUNTA(Sales_Data!$A$2:$A$251)
A4: 2b | B4: Total units sold | C4: =SUM(Sales_Data!$I$2:$I$251) -> 1357 | D4: =SUM(Sales_Data!$I$2:$I$251)
A5: 3a | B5: Average revenue per order | C5: =SUMPRODUCT(Sales_Data!$I$2:$I$251*Sales_Data!$J$2:$J$251*(1-Sales_Data!$K$2:$K$251))/COUNTA(Sales_Data!$A$2:$A$251) -> 6993.1882 | D5: =SUMPRODUCT(Sales_Data!$I$2:$I$251*Sales_Data!$J$2:$J$251*(1-Sales_Data!$K$2:$K$251))/COUNTA(Sales_Data!$A$2:$A$251) | E5: = AVERAGE(N:N) once you add column N
A6: 3b | B6: Highest order revenue | C6: =SUMPRODUCT(MAX(Sales_Data!$I$2:$I$251*Sales_Data!$J$2:$J$251*(1-Sales_Data!$K$2:$K$251))) -> 25497 | D6: =SUMPRODUCT(MAX(Sales_Data!$I$2:$I$251*Sales_Data!$J$2:$J$251*(1-Sales_Data!$K$2:$K$251))) | E6: = MAX(N:N)
A7: 3c | B7: Lowest order revenue | C7: =SUMPRODUCT(MIN(Sales_Data!$I$2:$I$251*Sales_Data!$J$2:$J$251*(1-Sales_Data!$K$2:$K$251))) -> 719.1 | D7: =SUMPRODUCT(MIN(Sales_Data!$I$2:$I$251*Sales_Data!$J$2:$J$251*(1-Sales_Data!$K$2:$K$251))) | E7: = MIN(N:N)
A8: 4a | B8: Delivered orders | C8: =COUNTIF(Sales_Data!$M$2:$M$251,"Delivered") -> 217 | D8: =COUNTIF(Sales_Data!$M$2:$M$251,"Delivered")
A9: 4b | B9: Returned orders | C9: =COUNTIF(Sales_Data!$M$2:$M$251,"Returned") -> 15 | D9: =COUNTIF(Sales_Data!$M$2:$M$251,"Returned")
A10: 4c | B10: Cancelled orders | C10: =COUNTIF(Sales_Data!$M$2:$M$251,"Cancelled") -> 18 | D10: =COUNTIF(Sales_Data!$M$2:$M$251,"Cancelled")
A11: 5a | B11: Revenue — West | C11: =SUMPRODUCT((Sales_Data!$D$2:$D$251="West")*Sales_Data!$I$2:$I$251*Sales_Data!$J$2:$J$251*(1-Sales_Data!$K$2:$K$251)) -> 506758.85 | D11: =SUMPRODUCT((Sales_Data!$D$2:$D$251="West")*Sales_Data!$I$2:$I$251*Sales_Data!$J$2:$J$251*(1-Sales_Data!$K$2:$K$251)) | E11: = SUMIF(D:D,"West",N:N) with column N
A12: 5b | B12: Net revenue — Delivered only | C12: =SUMPRODUCT((Sales_Data!$M$2:$M$251="Delivered")*Sales_Data!$I$2:$I$251*Sales_Data!$J$2:$J$251*(1-Sales_Data!$K$2:$K$251)) -> 1526078.9 | D12: =SUMPRODUCT((Sales_Data!$M$2:$M$251="Delivered")*Sales_Data!$I$2:$I$251*Sales_Data!$J$2:$J$251*(1-Sales_Data!$K$2:$K$251)) | E12: = SUMIF(M:M,"Delivered",N:N)
A13: 6 | B13: Orders placed in March | C13: =SUMPRODUCT(--(MONTH(Sales_Data!$B$2:$B$251)=3)) -> 15 | D13: =SUMPRODUCT(--(MONTH(Sales_Data!$B$2:$B$251)=3)) | E13: = COUNTIF(O:O,"Mar") with Month column
A14: 7 | B14: High Value orders (> 15,000) | C14: =SUMPRODUCT(--(Sales_Data!$I$2:$I$251*Sales_Data!$J$2:$J$251*(1-Sales_Data!$K$2:$K$251)>15000)) -> 24 | D14: =SUMPRODUCT(--(Sales_Data!$I$2:$I$251*Sales_Data!$J$2:$J$251*(1-Sales_Data!$K$2:$K$251)>15000)) | E14: = COUNTIF(P:P,"High Value")
A15: 8 | B15: Electronics · North · Delivered | C15: =SUMPRODUCT((Sales_Data!$G$2:$G$251="Electronics")*(Sales_Data!$D$2:$D$251="North")*(Sales_Data!$M$2:$M$251="Delivered")*Sales_Data!$I$2:$I$251*Sales_Data!$J$2:$J$251*(1-Sales_Data!$K$2:$K$251)) -> 98460.8 | D15: =SUMPRODUCT((Sales_Data!$G$2:$G$251="Electronics")*(Sales_Data!$D$2:$D$251="North")*(Sales_Data!$M$2:$M$251="Delivered")*Sales_Data!$I$2:$I$251*Sales_Data!$J$2:$J$251*(1-Sales_Data!$K$2:$K$251)) | E15: = SUMIFS(N:N,G:G,"Electronics",D:D,"North",M:M,"Delivered")
A16: 9a | B16: Avg discount — UPI | C16: =AVERAGEIF(Sales_Data!$L$2:$L$251,"UPI",Sales_Data!$K$2:$K$251) -> 0.089204545 | D16: =AVERAGEIF(Sales_Data!$L$2:$L$251,"UPI",Sales_Data!$K$2:$K$251)
A17: 9b | B17: Avg discount — COD | C17: =AVERAGEIF(Sales_Data!$L$2:$L$251,"COD",Sales_Data!$K$2:$K$251) -> 0.082954545 | D17: =AVERAGEIF(Sales_Data!$L$2:$L$251,"COD",Sales_Data!$K$2:$K$251)
A18: 10 | B18: Order ID with highest revenue | C18: =INDEX(Sales_Data!$A$2:$A$251,SUMPRODUCT(MAX((Sales_Data!$I$2:$I$251*Sales_Data!$J$2:$J$251*(1-Sales_Data!$K$2:$K$251)=C6)*(ROW(Sales_Data!$A$2:$A$251)-1)))) -> ORD1222 | D18: =INDEX(Sales_Data!$A$2:$A$251,SUMPRODUCT(MAX((Sales_Data!$I$2:$I$251*Sales_Data!$J$2:$J$251*(1-Sales_Data!$K$2:$K$251)=C6)*(ROW(Sales_Data!$A$2:$A$251)-1)))) | E18: Uses 3b as the max value
A19: 11 | B19: Total profit | C19: =SUMPRODUCT(Sales_Data!$I$2:$I$251*Sales_Data!$J$2:$J$251*(1-Sales_Data!$K$2:$K$251))-SUMPRODUCT(Sales_Data!$I$2:$I$251*SUMIF(Product_Master!$A$2:$A$13,Sales_Data!$H$2:$H$251,Product_Master!$D$2:$D$13)) -> 647597.05 | D19: =SUMPRODUCT(Sales_Data!$I$2:$I$251*Sales_Data!$J$2:$J$251*(1-Sales_Data!$K$2:$K$251))-SUMPRODUCT(Sales_Data!$I$2:$I$251*SUMIF(Product_Master!$A$2:$A$13,Sales_Data!$H$2:$H$251,Product_Master!$D$2:$D$13)) | E19: Per row: =VLOOKUP(H2,Product_Master!$A$2:$D$13,4,FALSE) then =N2-I2*Q2
A20: 12 | B20: Orders: discount ≥10% & qty > 5 | C20: =COUNTIFS(Sales_Data!$K$2:$K$251,">=0.1",Sales_Data!$I$2:$I$251,">5") -> 36 | D20: =COUNTIFS(Sales_Data!$K$2:$K$251,">=0.1",Sales_Data!$I$2:$I$251,">5")
A21: 13 | B21: Return rate — Clothing | C21: =COUNTIFS(Sales_Data!$G$2:$G$251,"Clothing",Sales_Data!$M$2:$M$251,"Returned")/COUNTIF(Sales_Data!$G$2:$G$251,"Clothing") -> 0.038461538 | D21: =COUNTIFS(Sales_Data!$G$2:$G$251,"Clothing",Sales_Data!$M$2:$M$251,"Returned")/COUNTIF(Sales_Data!$G$2:$G$251,"Clothing") | E21: See table D on Answer_Tables
A22: 14 | B22: Weekend orders | C22: =SUMPRODUCT(--(WEEKDAY(Sales_Data!$B$2:$B$251,2)>5)) -> 83 | D22: =SUMPRODUCT(--(WEEKDAY(Sales_Data!$B$2:$B$251,2)>5))
A23: 15 | B23: Avg delivery days — West | C23: =SUMPRODUCT((Sales_Data!$D$2:$D$251="West")*(Sales_Data!$C$2:$C$251<>"")*(Sales_Data!$C$2:$C$251-Sales_Data!$B$2:$B$251))/SUMPRODUCT((Sales_Data!$D$2:$D$251="West")*(Sales_Data!$C$2:$C$251<>"")) -> 5.9666667 | D23: =SUMPRODUCT((Sales_Data!$D$2:$D$251="West")*(Sales_Data!$C$2:$C$251<>"")*(Sales_Data!$C$2:$C$251-Sales_Data!$B$2:$B$251))/SUMPRODUCT((Sales_Data!$D$2:$D$251="West")*(Sales_Data!$C$2:$C$251<>"")) | E23: Per row: =IF(C2="","",C2-B2) then AVERAGEIFS
A24: 16 | B24: Salespeople who met target | C24: =COUNTIF(Answer_Tables!F3:F10,"Target Met") -> 4 | D24: =COUNTIF(Answer_Tables!F3:F10,"Target Met") | E24: Full table: Answer_Tables section A
A25: 17 | B25: Top salesperson | C25: =Answer_Tables!B12 -> Vikram Shah | D25: =Answer_Tables!B12 | E25: Answer_Tables section A
A26: 18 | B26: Peak revenue month | C26: =INDEX(Answer_Tables!B23:B34,MATCH(MAX(Answer_Tables!C23:C34),Answer_Tables!C23:C34,0)) -> Nov | D26: =INDEX(Answer_Tables!B23:B34,MATCH(MAX(Answer_Tables!C23:C34),Answer_Tables!C23:C34,0)) | E26: Answer_Tables section B (also cumulative & MoM)
A27: 19 | B27: Grand total of Region × Category grid | C27: =Answer_Tables!F44 -> 1748297 | D27: =Answer_Tables!F44 | E27: Answer_Tables section C — must equal Q1
A28: 20 | B28: Electronics share of revenue | C28: =Answer_Tables!B47 -> 0.26878673 | D28: =Answer_Tables!B47 | E28: Answer_Tables section C
A29: 21 | B29: 3rd-ranked salesperson | C29: =Answer_Tables!B18 -> Rohit Das | D29: =Answer_Tables!B18 | E29: Answer_Tables top-3 table
A30: 22 | B30: Unique cities | C30: =SUMPRODUCT(1/COUNTIF(Sales_Data!$E$2:$E$251,Sales_Data!$E$2:$E$251)) -> 12 | D30: =SUMPRODUCT(1/COUNTIF(Sales_Data!$E$2:$E$251,Sales_Data!$E$2:$E$251))
A31: 23 | B31: Pivot grand total (should match Q1) | C31: =C2 -> 1748297.1 | D31: =C2 | E31: Your PivotTable's Grand Total must show this
A32: 26 | B32: Cleaned name — row 1 | C32: =Answer_Tables!A60 -> Riya Sharma | D32: =Answer_Tables!A60 | E32: Answer_Tables section E: =PROPER(TRIM(A2))
A33: 27 | B33: First name — row 1 | C33: =Answer_Tables!B60 -> Riya | D33: =Answer_Tables!B60 | E33: =LEFT(F2,FIND(" ",F2)-1)
A34: 28 | B34: Phone — row 1 | C34: =Answer_Tables!C60 -> 9876543210 | D34: =Answer_Tables!C60 | E34: =RIGHT(SUBSTITUTE(SUBSTITUTE(SUBSTITUTE(TRIM(B2)," ",""),"-",""),"+",""),10)
A35: 29 | B35: Total cleaned amount | C35: =Answer_Tables!E74 -> 21644 | D35: =Answer_Tables!E74 | E35: =VALUE(SUBSTITUTE(SUBSTITUTE(SUBSTITUTE(SUBSTITUTE(D2,"₹",""),"Rs.","")," ",""),",",""))
A36: 30 | B36: Unique customers after cleaning | C36: =Answer_Tables!B73 -> 9 | D36: =Answer_Tables!B73 | E36: Duplicates are the same person typed differently
A39: Q24, Q25 (conditional formatting, dashboard) are visual — no single answer cell.
